Workbook

Sheet 红宝书去重版
A1: 顺序 | B1: 乱序 | C1: 假名 | D1: 汉字/外文 | E1: 形 | G1: 副 | H1: 叠 | I1: 特 | J1: 图源 | N1: 音源 | S1: 1遍 | T1: 2遍 | U1: 3遍 | V1: 正确率 | W1: 已学习 | Y1: 特殊备注 | Z1: 总进度 | AA1: N5进度 | AB1: N4进度 | AC1: N3进度 | AD1: N2进度 | AE1: N1进度
C2: 9574 | Z2: =COUNTA($W$3:$W$9575)/9574 -> 0 | AA2: =COUNTIFS($W$3:$W$9575,"<>",$X$3:$X$9575,"N5")/1000 -> 0 | AB2: =COUNTIFS($W$3:$W$9575,"<>",$X$3:$X$9575,"N4")/1121 -> 0 | AC2: =COUNTIFS($W$3:$W$9575,"<>",$X$3:$X$9575,"N3")/2072 -> 0 | AD2: =COUNTIFS($W$3:$W$9575,"<>",$X$3:$X$9575,"N2")/2328 -> 0 | AE2: =COUNTIFS($W$3:$W$9575,"<>",$X$3:$X$9575,"N1")/3053 -> 0
A3: 1 | B3: =RAND() -> 0.33361135 | C3: ああ | J3: =HYPERLINK(K3,"➸") -> ➸ | K3: =词典存放目录!$A$1&L3&M3 -> F:\《自创文法查阅Excel》4.1备份\《B词汇·红宝书》\红宝书15版图片\1-ああ.jpg | L3: \红宝书15版图片\ | M3: 1-ああ.jpg | N3: =HYPERLINK(R3,"▶") -> ▶ | O3: \红宝书MP3分割\01 n5-あ ( | P3: 1 | Q3: ).mp3 | R3: =词典存放目录!$A$1&O3&P3&Q3 -> F:\《自创文法查阅Excel》4.1备份\《B词汇·红宝书》\红宝书MP3分割\01 n5-あ (1).mp3 | V3: =IF(COUNTA(S3:U3)=0,"",COUNTIF(S3:U3,"0")/COUNTA(S3:U3)) | X3: N5 | Z3: =Z2 -> 0 | AA3: =AA2 -> 0 | AB3: =AB2 -> 0 | AC3: =AC2 -> 0 | AD3: =AD2 -> 0 | AE3: =AE2 -> 0
A4: 2 | B4: =RAND() -> 0.054255805 | C4: アイスクリーム | D4: ice-cream | J4: =HYPERLINK(K4,"➸") -> ➸ | K4: =词典存放目录!$A$1&L4&M4 -> F:\《自创文法查阅Excel》4.1备份\《B词汇·红宝书》\红宝书15版图片\2-アイスクリーム【ice-cream】.jpg | L4: \红宝书15版图片\ | M4: 2-アイスクリーム【ice-cream】.jpg | N4: =HYPERLINK(R4,"▶") -> ▶ | O4: \红宝书MP3分割\01 n5-あ ( | P4: 2 | Q4: ).mp3 | R4: =词典存放目录!$A$1&O4&P4&Q4 -> F:\《自创文法查阅Excel》4.1备份\《B词汇·红宝书》\红宝书MP3分割\01 n5-あ (2).mp3 | V4: =IF(COUNTA(S4:U4)=0,"",COUNTIF(S4:U4,"0")/COUNTA(S4:U4)) | X4: N5 | Z4: =1-Z3 -> 1 | AA4: =1-AA3 -> 1 | AB4: =1-AB3 -> 1 | AC4: =1-AC3 -> 1 | AD4: =1-AD3 -> 1 | AE4: =1-AE3 -> 1
A5: 3 | B5: =RAND() -> 0.84567668 | C5: あう | D5: 会う | J5: =HYPERLINK(K5,"➸") -> ➸ | K5: =词典存放目录!$A$1&L5&M5 -> F:\《自创文法查阅Excel》4.1备份\《B词汇·红宝书》\红宝书15版图片\3-あう【会う】.jpg | L5: \红宝书15版图片\ | M5: 3-あう【会う】.jpg | N5: =HYPERLINK(R5,"▶") -> ▶ | O5: \红宝书MP3分割\01 n5-あ ( | P5: 3 | Q5: ).mp3 | R5: =词典存放目录!$A$1&O5&P5&Q5 -> F:\《自创文法查阅Excel》4.1备份\《B词汇·红宝书》\红宝书MP3分割\01 n5-あ (3).mp3 | V5: =IF(COUNTA(S5:U5)=0,"",COUNTIF(S5:U5,"0")/COUNTA(S5:U5)) | X5: N5
A6: 4 | B6: =RAND() -> 0.75722748 | C6: あお | D6: 青 | J6: =HYPERLINK(K6,"➸") -> ➸ | K6: =词典存放目录!$A$1&L6&M6 -> F:\《自创文法查阅Excel》4.1备份\《B词汇·红宝书》\红宝书15版图片\4-あお【青】.jpg | L6: \红宝书15版图片\ | M6: 4-あお【青】.jpg | N6: =HYPERLINK(R6,"▶") -> ▶ | O6: \红宝书MP3分割\01 n5-あ ( | P6: 4 | Q6: ).mp3 | R6: =词典存放目录!$A$1&O6&P6&Q6 -> F:\《自创文法查阅Excel》4.1备份\《B词汇·红宝书》\红宝书MP3分割\01 n5-あ (4).mp3 | V6: =IF(COUNTA(S6:U6)=0,"",COUNTIF(S6:U6,"0")/COUNTA(S6:U6)) | X6: N5
A7: 5 | B7: =RAND() -> 0.028593637 | C7: あおい | D7: 青い | E7: A1 | J7: =HYPERLINK(K7,"➸") -> ➸ | K7: =词典存放目录!$A$1&L7&M7 -> F:\《自创文法查阅Excel》4.1备份\《B词汇·红宝书》\红宝书15版图片\5-あおい【青い】.jpg | L7: \红宝书15版图片\ | M7: 5-あおい【青い】.jpg | N7: =HYPERLINK(R7,"▶") -> ▶ | O7: \红宝书MP3分割\01 n5-あ ( | P7: 5 | Q7: ).mp3 | R7: =词典存放目录!$A$1&O7&P7&Q7 -> F:\《自创文法查阅Excel》4.1备份\《B词汇·红宝书》\红宝书MP3分割\01 n5-あ (5).mp3 | V7: =IF(COUNTA(S7:U7)=0,"",COUNTIF(S7:U7,"0")/COUNTA(S7:U7)) | X7: N5
A8: 6 | B8: =RAND() -> 0.50277074 | C8: あか | D8: 赤 | J8: =HYPERLINK(K8,"➸") -> ➸ | K8: =词典存放目录!$A$1&L8&M8 -> F:\《自创文法查阅Excel》4.1备份\《B词汇·红宝书》\红宝书15版图片\6-あか【赤】.jpg | L8: \红宝书15版图片\ | M8: 6-あか【赤】.jpg | N8: =HYPERLINK(R8,"▶") -> ▶ | O8: \红宝书MP3分割\01 n5-あ ( | P8: 6 | Q8: ).mp3 | R8: =词典存放目录!$A$1&O8&P8&Q8 -> F:\《自创文法查阅Excel》4.1备份\《B词汇·红宝书》\红宝书MP3分割\01 n5-あ (6).mp3 | V8: =IF(COUNTA(S8:U8)=0,"",COUNTIF(S8:U8,"0")/COUNTA(S8:U8)) | X8: N5
A9: 7 | B9: =RAND() -> 0.24619445 | C9: あかい | D9: 赤い | E9: A1 | J9: =HYPERLINK(K9,"➸") -> ➸ | K9: =词典存放目录!$A$1&L9&M9 -> F:\《自创文法查阅Excel》4.1备份\《B词汇·红宝书》\红宝书15版图片\7-あかい【赤い】.jpg | L9: \红宝书15版图片\ | M9: 7-あかい【赤い】.jpg | N9: =HYPERLINK(R9,"▶") -> ▶ | O9: \红宝书MP3分割\01 n5-あ ( | P9: 7 | Q9: ).mp3 | R9: =词典存放目录!$A$1&O9&P9&Q9 -> F:\《自创文法查阅Excel》4.1备份\《B词汇·红宝书》\红宝书MP3分割\01 n5-あ (7).mp3 | V9: =IF(COUNTA(S9:U9)=0,"",COUNTIF(S9:U9,"0")/COUNTA(S9:U9)) | X9: N5
A10: 8 | B10: =RAND() -> 0.91919995 | C10: あかるい | D10: 明るい | J10: =HYPERLINK(K10,"➸") -> ➸ | K10: =词典存放目录!$A$1&L10&M10 -> F:\《自创文法查阅Excel》4.1备份\《B词汇·红宝书》\红宝书15版图片\8-あかるい【明るい】.jpg | L10: \红宝书15版图片\ | M10: 8-あかるい【明るい】.jpg | N10: =HYPERLINK(R10,"▶") -> ▶ | O10: \红宝书MP3分割\01 n5-あ ( | P10: 8 | Q10: ).mp3 | R10: =词典存放目录!$A$1&O10&P10&Q10 -> F:\《自创文法查阅Excel》4.1备份\《B词汇·红宝书》\红宝书MP3分割\01 n5-あ (8).mp3 | V10: =IF(COUNTA(S10:U10)=0,"",COUNTIF(S10:U10,"0")/COUNTA(S10:U10)) | X10: N5
A11: 9 | B11: =RAND() -> 0.59809256 | C11: あき | D11: 秋 | J11: =HYPERLINK(K11,"➸") -> ➸ | K11: =词典存放目录!$A$1&L11&M11 -> F:\《自创文法查阅Excel》4.1备份\《B词汇·红宝书》\红宝书15版图片\9-あき【秋】.jpg | L11: \红宝书15版图片\ | M11: 9-あき【秋】.jpg | N11: =HYPERLINK(R11,"▶") -> ▶ | O11: \红宝书MP3分割\01 n5-あ ( | P11: 9 | Q11: ).mp3 | R11: =词典存放目录!$A$1&O11&P11&Q11 -> F:\《自创文法查阅Excel》4.1备份\《B词汇·红宝书》\红宝书MP3分割\01 n5-あ (9).mp3 | V11: =IF(COUNTA(S11:U11)=0,"",COUNTIF(S11:U11,"0")/COUNTA(S11:U11)) | X11: N5
A12: 10 | B12: =RAND() -> 0.31604149 | C12: あく | D12: 開く | J12: =HYPERLINK(K12,"➸") -> ➸ | K12: =词典存放目录!$A$1&L12&M12 -> F:\《自创文法查阅Excel》4.1备份\《B词汇·红宝书》\红宝书15版图片\10-あく【開く】.jpg | L12: \红宝书15版图片\ | M12: 10-あく【開く】.jpg | N12: =HYPERLINK(R12,"▶") -> ▶ | O12: \红宝书MP3分割\01 n5-あ ( | P12: 10 | Q12: ).mp3 | R12: =词典存放目录!$A$1&O12&P12&Q12 -> F:\《自创文法查阅Excel》4.1备份\《B词汇·红宝书》\红宝书MP3分割\01 n5-あ (10).mp3 | V12: =IF(COUNTA(S12:U12)=0,"",COUNTIF(S12:U12,"0")/COUNTA(S12:U12)) | X12: N5
A13: 11 | B13: =RAND() -> 0.70873494 | C13: あける | D13: 開ける | J13: =HYPERLINK(K13,"➸") -> ➸ | K13: =词典存放目录!$A$1&L13&M13 -> F:\《自创文法查阅Excel》4.1备份\《B词汇·红宝书》\红宝书15版图片\11-あける【開ける】.jpg | L13: \红宝书15版图片\ | M13: 11-あける【開ける】.jpg | N13: =HYPERLINK(R13,"▶") -> ▶ | O13: \红宝书MP3分割\01 n5-あ ( | P13: 11 | Q13: ).mp3 | R13: =词典存放目录!$A$1&O13&P13&Q13 -> F:\《自创文法查阅Excel》4.1备份\《B词汇·红宝书》\红宝书MP3分割\01 n5-あ (11).mp3 | V13: =IF(COUNTA(S13:U13)=0,"",COUNTIF(S13:U13,"0")/COUNTA(S13:U13)) | X13: N5
A14: 12 | B14: =RAND() -> 0.16400377 | C14: あげる | D14: 上げる | J14: =HYPERLINK(K14,"➸") -> ➸ | K14: =词典存放目录!$A$1&L14&M14 -> F:\《自创文法查阅Excel》4.1备份\《B词汇·红宝书》\红宝书15版图片\12-あげる【上げる】.jpg | L14: \红宝书15版图片\ | M14: 12-あげる【上げる】.jpg | N14: =HYPERLINK(R14,"▶") -> ▶ | O14: \红宝书MP3分割\01 n5-あ ( | P14: 12 | Q14: ).mp3 | R14: =词典存放目录!$A$1&O14&P14&Q14 -> F:\《自创文法查阅Excel》4.1备份\《B词汇·红宝书》\红宝书MP3分割\01 n5-あ (12).mp3 | V14: =IF(COUNTA(S14:U14)=0,"",COUNTIF(S14:U14,"0")/COUNTA(S14:U14)) | X14: N5
A15: 13 | B15: =RAND() -> 0.95637986 | C15: あさ | D15: 朝 | J15: =HYPERLINK(K15,"➸") -> ➸ | K15: =词典存放目录!$A$1&L15&M15 -> F:\《自创文法查阅Excel》4.1备份\《B词汇·红宝书》\红宝书15版图片\13-あさ【朝】.jpg | L15: \红宝书15版图片\ | M15: 13-あさ【朝】.jpg | N15: =HYPERLINK(R15,"▶") -> ▶ | O15: \红宝书MP3分割\01 n5-あ ( | P15: 13 | Q15: ).mp3 | R15: =词典存放目录!$A$1&O15&P15&Q15 -> F:\《自创文法查阅Excel》4.1备份\《B词汇·红宝书》\红宝书MP3分割\01 n5-あ (13).mp3 | X15: N5
A16: 14 | B16: =RAND() -> 0.12673403 | C16: あさごはん | D16: 朝ご飯 | J16: =HYPERLINK(K16,"➸") -> ➸ | K16: =词典存放目录!$A$1&L16&M16 -> F:\《自创文法查阅Excel》4.1备份\《B词汇·红宝书》\红宝书15版图片\14-あさごはん【朝ご飯】.jpg | L16: \红宝书15版图片\ | M16: 14-あさごはん【朝ご飯】.jpg | N16: =HYPERLINK(R16,"▶") -> ▶ | O16: \红宝书MP3分割\01 n5-あ ( | P16: 14 | Q16: ).mp3 | R16: =词典存放目录!$A$1&O16&P16&Q16 -> F:\《自创文法查阅Excel》4.1备份\《B词汇·红宝书》\红宝书MP3分割\01 n5-あ (14).mp3 | V16: =IF(COUNTA(S16:U16)=0,"",COUNTIF(S16:U16,"0")/COUNTA(S16:U16)) | X16: N5
A17: 15 | B17: =RAND() -> 0.95372296 | C17: あさって | D17: 明後日 | J17: =HYPERLINK(K17,"➸") -> ➸ | K17: =词典存放目录!$A$1&L17&M17 -> F:\《自创文法查阅Excel》4.1备份\《B词汇·红宝书》\红宝书15版图片\15-あさって【明後日】.jpg | L17: \红宝书15版图片\ | M17: 15-あさって【明後日】.jpg | N17: =HYPERLINK(R17,"▶") -> ▶ | O17: \红宝书MP3分割\01 n5-あ ( | P17: 15 | Q17: ).mp3 | R17: =词典存放目录!$A$1&O17&P17&Q17 -> F:\《自创文法查阅Excel》4.1备份\《B词汇·红宝书》\红宝书MP3分割\01 n5-あ (15).mp3 | V17: =IF(COUNTA(S17:U17)=0,"",COUNTIF(S17:U17,"0")/COUNTA(S17:U17)) | X17: N5
A18: 16 | B18: =RAND() -> 0.36951353 | C18: あし | D18: 足 | J18: =HYPERLINK(K18,"➸") -> ➸ | K18: =词典存放目录!$A$1&L18&M18 -> F:\《自创文法查阅Excel》4.1备份\《B词汇·红宝书》\红宝书15版图片\16-あし【足】.jpg | L18: \红宝书15版图片\ | M18: 16-あし【足】.jpg | N18: =HYPERLINK(R18,"▶") -> ▶ | O18: \红宝书MP3分割\01 n5-あ ( | P18: 16 | Q18: ).mp3 | R18: =词典存放目录!$A$1&O18&P18&Q18 -> F:\《自创文法查阅Excel》4.1备份\《B词汇·红宝书》\红宝书MP3分割\01 n5-あ (16).mp3 | V18: =IF(COUNTA(S18:U18)=0,"",COUNTIF(S18:U18,"0")/COUNTA(S18:U18)) | X18: N5
A19: 17 | B19: =RAND() -> 0.88453654 | C19: あした | D19: 明日 | J19: =HYPERLINK(K19,"➸") -> ➸ | K19: =词典存放目录!$A$1&L19&M19 -> F:\《自创文法查阅Excel》4.1备份\《B词汇·红宝书》\红宝书15版图片\17-あした【明日】.jpg | L19: \红宝书15版图片\ | M19: 17-あした【明日】.jpg | N19: =HYPERLINK(R19,"▶") -> ▶ | O19: \红宝书MP3分割\01 n5-あ ( | P19: 17 | Q19: ).mp3 | R19: =词典存放目录!$A$1&O19&P19&Q19 -> F:\《自创文法查阅Excel》4.1备份\《B词汇·红宝书》\红宝书MP3分割\01 n5-あ (17).mp3 | V19: =IF(COUNTA(S19:U19)=0,"",COUNTIF(S19:U19,"0")/COUNTA(S19:U19)) | X19: N5
A20: 18 | B20: =RAND() -> 0.93793452 | C20: あそこ | J20: =HYPERLINK(K20,"➸") -> ➸ | K20: =词典存放目录!$A$1&L20&M20 -> F:\《自创文法查阅Excel》4.1备份\《B词汇·红宝书》\红宝书15版图片\18-あそこ.jpg | L20: \红宝书15版图片\ | M20: 18-あそこ.jpg | N20: =HYPERLINK(R20,"▶") -> ▶ | O20: \红宝书MP3分割\01 n5-あ ( | P20: 18 | Q20: ).mp3 | R20: =词典存放目录!$A$1&O20&P20&Q20 -> F:\《自创文法查阅Excel》4.1备份\《B词汇·红宝书》\红宝书MP3分割\01 n5-あ (18).mp3 | V20: =IF(COUNTA(S20:U20)=0,"",COUNTIF(S20:U20,"0")/COUNTA(S20:U20)) | X20: N5
A21: 19 | B21: =RAND() -> 0.45114169 | C21: あそぶ | D21: 遊ぶ | J21: =HYPERLINK(K21,"➸") -> ➸ | K21: =词典存放目录!$A$1&L21&M21 -> F:\《自创文法查阅Excel》4.1备份\《B词汇·红宝书》\红宝书15版图片\19-あそぶ【遊ぶ】.jpg | L21: \红宝书15版图片\ | M21: 19-あそぶ【遊ぶ】.jpg | N21: =HYPERLINK(R21,"▶") -> ▶ | O21: \红宝书MP3分割\01 n5-あ ( | P21: 19 | Q21: ).mp3 | R21: =词典存放目录!$A$1&O21&P21&Q21 -> F:\《自创文法查阅Excel》4.1备份\《B词汇·红宝书》\红宝书MP3分割\01 n5-あ (19).mp3 | V21: =IF(COUNTA(S21:U21)=0,"",COUNTIF(S21:U21,"0")/COUNTA(S21:U21)) | X21: N5
A22: 20 | B22: =RAND() -> 0.061972685 | C22: あたし | J22: =HYPERLINK(K22,"➸") -> ➸ | K22: =词典存放目录!$A$1&L22&M22 -> F:\《自创文法查阅Excel》4.1备份\《B词汇·红宝书》\红宝书15版图片\20-あたし.jpg | L22: \红宝书15版图片\ | M22: 20-あたし.jpg | N22: =HYPERLINK(R22,"▶") -> ▶ | O22: \红宝书MP3分割\01 n5-あ ( | P22: 20 | Q22: ).mp3 | R22: =词典存放目录!$A$1&O22&P22&Q22 -> F:\《自创文法查阅Excel》4.1备份\《B词汇·红宝书》\红宝书MP3分割\01 n5-あ (20).mp3 | V22: =IF(COUNTA(S22:U22)=0,"",COUNTIF(S22:U22,"0")/COUNTA(S22:U22)) | X22: N5
A23: 21 | B23: =RAND() -> 0.055127142 | C23: あたたかい | D23: 温/暖かい | E23: A1 | J23: =HYPERLINK(K23,"➸") -> ➸ | K23: =词典存放目录!$A$1&L23&M23 -> F:\《自创文法查阅Excel》4.1备份\《B词汇·红宝书》\红宝书15版图片\21-あたたかい【温·暖かい】.jpg | L23: \红宝书15版图片\ | M23: 21-あたたかい【温·暖かい】.jpg | N23: =HYPERLINK(R23,"▶") -> ▶ | O23: \红宝书MP3分割\01 n5-あ ( | P23: 21 | Q23: ).mp3 | R23: =词典存放目录!$A$1&O23&P23&Q23 -> F:\《自创文法查阅Excel》4.1备份\《B词汇·红宝书》\红宝书MP3分割\01 n5-あ (21).mp3 | V23: =IF(COUNTA(S23:U23)=0,"",COUNTIF(S23:U23,"0")/COUNTA(S23:U23)) | X23: N5
A24: 22 | B24: =RAND() -> 0.3582911 | C24: あたま | D24: 頭 | J24: =HYPERLINK(K24,"➸") -> ➸ | K24: =词典存放目录!$A$1&L24&M24 -> F:\《自创文法查阅Excel》4.1备份\《B词汇·红宝书》\红宝书15版图片\22-あたま【頭】.jpg | L24: \红宝书15版图片\ | M24: 22-あたま【頭】.jpg | N24: =HYPERLINK(R24,"▶") -> ▶ | O24: \红宝书MP3分割\01 n5-あ ( | P24: 22 | Q24: ).mp3 | R24: =词典存放目录!$A$1&O24&P24&Q24 -> F:\《自创文法查阅Excel》4.1备份\《B词汇·红宝书》\红宝书MP3分割\01 n5-あ (22).mp3 | V24: =IF(COUNTA(S24:U24)=0,"",COUNTIF(S24:U24,"0")/COUNTA(S24:U24)) | X24: N5
A25: 23 | B25: =RAND() -> 0.91585352 | C25: あたらしい | D25: 新しい | E25: A1 | J25: =HYPERLINK(K25,"➸") -> ➸ | K25: =词典存放目录!$A$1&L25&M25 -> F:\《自创文法查阅Excel》4.1备份\《B词汇·红宝书》\红宝书15版图片\23-あたらしい【新しい】.jpg | L25: \红宝书15版图片\ | M25: 23-あたらしい【新しい】.jpg | N25: =HYPERLINK(R25,"▶") -> ▶ | O25: \红宝书MP3分割\01 n5-あ ( | P25: 23 | Q25: ).mp3 | R25: =词典存放目录!$A$1&O25&P25&Q25 -> F:\《自创文法查阅Excel》4.1备份\《B词汇·红宝书》\红宝书MP3分割\01 n5-あ (23).mp3 | V25: =IF(COUNTA(S25:U25)=0,"",COUNTIF(S25:U25,"0")/COUNTA(S25:U25)) | X25: N5
A26: 24 | B26: =RAND() -> 0.28561552 | C26: あちら | J26: =HYPERLINK(K26,"➸") -> ➸ | K26: =词典存放目录!$A$1&L26&M26 -> F:\《自创文法查阅Excel》4.1备份\《B词汇·红宝书》\红宝书15版图片\24-あちら.jpg | L26: \红宝书15版图片\ | M26: 24-あちら.jpg | N26: =HYPERLINK(R26,"▶") -> ▶ | O26: \红宝书MP3分割\01 n5-あ ( | P26: 24 | Q26: ).mp3 | R26: =词典存放目录!$A$1&O26&P26&Q26 -> F:\《自创文法查阅Excel》4.1备份\《B词汇·红宝书》\红宝书MP3分割\01 n5-あ (24).mp3 | V26: =IF(COUNTA(S26:U26)=0,"",COUNTIF(S26:U26,"0")/COUNTA(S26:U26)) | X26: N5
A27: 25 | B27: =RAND() -> 0.9248517 | C27: あっ | J27: =HYPERLINK(K27,"➸") -> ➸ | K27: =词典存放目录!$A$1&L27&M27 -> F:\《自创文法查阅Excel》4.1备份\《B词汇·红宝书》\红宝书15版图片\25-あっ.jpg | L27: \红宝书15版图片\ | M27: 25-あっ.jpg | N27: =HYPERLINK(R27,"▶") -> ▶ | O27: \红宝书MP3分割\01 n5-あ ( | P27: 25 | Q27: ).mp3 | R27: =词典存放目录!$A$1&O27&P27&Q27 -> F:\《自创文法查阅Excel》4.1备份\《B词汇·红宝书》\红宝书MP3分割\01 n5-あ (25).mp3 | V27: =IF(COUNTA(S27:U27)=0,"",COUNTIF(S27:U27,"0")/COUNTA(S27:U27)) | X27: N5
A28: 26 | B28: =RAND() -> 0.44141059 | C28: あつい | D28: 暑い | E28: A1 | J28: =HYPERLINK(K28,"➸") -> ➸ | K28: =词典存放目录!$A$1&L28&M28 -> F:\《自创文法查阅Excel》4.1备份\《B词汇·红宝书》\红宝书15版图片\26-あつい【暑い】.jpg | L28: \红宝书15版图片\ | M28: 26-あつい【暑い】.jpg | N28: =HYPERLINK(R28,"▶") -> ▶ | O28: \红宝书MP3分割\01 n5-あ ( | P28: 26 | Q28: ).mp3 | R28: =词典存放目录!$A$1&O28&P28&Q28 -> F:\《自创文法查阅Excel》4.1备份\《B词汇·红宝书》\红宝书MP3分割\01 n5-あ (26).mp3 | V28: =IF(COUNTA(S28:U28)=0,"",COUNTIF(S28:U28,"0")/COUNTA(S28:U28)) | X28: N5
A29: 27 | B29: =RAND() -> 0.55183528 | C29: あつい | D29: 熱い | E29: A1 | J29: =HYPERLINK(K29,"➸") -> ➸ | K29: =词典存放目录!$A$1&L29&M29 -> F:\《自创文法查阅Excel》4.1备份\《B词汇·红宝书》\红宝书15版图片\27-あつい【熱い】.jpg | L29: \红宝书15版图片\ | M29: 27-あつい【熱い】.jpg | N29: =HYPERLINK(R29,"▶") -> ▶ | O29: \红宝书MP3分割\01 n5-あ ( | P29: 27 | Q29: ).mp3 | R29: =词典存放目录!$A$1&O29&P29&Q29 -> F:\《自创文法查阅Excel》4.1备份\《B词汇·红宝书》\红宝书MP3分割\01 n5-あ (27).mp3 | V29: =IF(COUNTA(S29:U29)=0,"",COUNTIF(S29:U29,"0")/COUNTA(S29:U29)) | X29: N5
A30: 28 | B30: =RAND() -> 0.013537471 | C30: あつい | D30: 厚い | E30: A1 | J30: =HYPERLINK(K30,"➸") -> ➸ | K30: =词典存放目录!$A$1&L30&M30 -> F:\《自创文法查阅Excel》4.1备份\《B词汇·红宝书》\红宝书15版图片\28-あつい【厚い】.jpg | L30: \红宝书15版图片\ | M30: 28-あつい【厚い】.jpg | N30: =HYPERLINK(R30,"▶") -> ▶ | O30: \红宝书MP3分割\01 n5-あ ( | P30: 28 | Q30: ).mp3 | R30: =词典存放目录!$A$1&O30&P30&Q30 -> F:\《自创文法查阅Excel》4.1备份\《B词汇·红宝书》\红宝书MP3分割\01 n5-あ (28).mp3 | V30: =IF(COUNTA(S30:U30)=0,"",COUNTIF(S30:U30,"0")/COUNTA(S30:U30)) | X30: N5
A31: 29 | B31: =RAND() -> 0.10729077 | C31: あっち | J31: =HYPERLINK(K31,"➸") -> ➸ | K31: =词典存放目录!$A$1&L31&M31 -> F:\《自创文法查阅Excel》4.1备份\《B词汇·红宝书》\红宝书15版图片\29-あっち.jpg | L31: \红宝书15版图片\ | M31: 29-あっち.jpg | N31: =HYPERLINK(R31,"▶") -> ▶ | O31: \红宝书MP3分割\01 n5-あ ( | P31: 29 | Q31: ).mp3 | R31: =词典存放目录!$A$1&O31&P31&Q31 -> F:\《自创文法查阅Excel》4.1备份\《B词汇·红宝书》\红宝书MP3分割\01 n5-あ (29).mp3 | V31: =IF(COUNTA(S31:U31)=0,"",COUNTIF(S31:U31,"0")/COUNTA(S31:U31)) | X31: N5
A32: 30 | B32: =RAND() -> 0.88139985 | C32: あと | D32: 後 | J32: =HYPERLINK(K32,"➸") -> ➸ | K32: =词典存放目录!$A$1&L32&M32 -> F:\《自创文法查阅Excel》4.1备份\《B词汇·红宝书》\红宝书15版图片\30-あと【後】.jpg | L32: \红宝书15版图片\ | M32: 30-あと【後】.jpg | N32: =HYPERLINK(R32,"▶") -> ▶ | O32: \红宝书MP3分割\01 n5-あ ( | P32: 30 | Q32: ).mp3 | R32: =词典存放目录!$A$1&O32&P32&Q32 -> F:\《自创文法查阅Excel》4.1备份\《B词汇·红宝书》\红宝书MP3分割\01 n5-あ (30).mp3 | V32: =IF(COUNTA(S32:U32)=0,"",COUNTIF(S32:U32,"0")/COUNTA(S32:U32)) | X32: N5
A33: 31 | B33: =RAND() -> 0.78546598 | C33: あなた | J33: =HYPERLINK(K33,"➸") -> ➸ | K33: =词典存放目录!$A$1&L33&M33 -> F:\《自创文法查阅Excel》4.1备份\《B词汇·红宝书》\红宝书15版图片\31-あなた.jpg | L33: \红宝书15版图片\ | M33: 31-あなた.jpg | N33: =HYPERLINK(R33,"▶") -> ▶ | O33: \红宝书MP3分割\01 n5-あ ( | P33: 31 | Q33: ).mp3 | R33: =词典存放目录!$A$1&O33&P33&Q33 -> F:\《自创文法查阅Excel》4.1备份\《B词汇·红宝书》\红宝书MP3分割\01 n5-あ (31).mp3 | V33: =IF(COUNTA(S33:U33)=0,"",COUNTIF(S33:U33,"0")/COUNTA(S33:U33)) | X33: N5
A34: 32 | B34: =RAND() -> 0.77548621 | C34: あに | D34: 兄 | J34: =HYPERLINK(K34,"➸") -> ➸ | K34: =词典存放目录!$A$1&L34&M34 -> F:\《自创文法查阅Excel》4.1备份\《B词汇·红宝书》\红宝书15版图片\32-あに【兄】.jpg | L34: \红宝书15版图片\ | M34: 32-あに【兄】.jpg | N34: =HYPERLINK(R34,"▶") -> ▶ | O34: \红宝书MP3分割\01 n5-あ ( | P34: 32 | Q34: ).mp3 | R34: =词典存放目录!$A$1&O34&P34&Q34 -> F:\《自创文法查阅Excel》4.1备份\《B词汇·红宝书》\红宝书MP3分割\01 n5-あ (32).mp3 | V34: =IF(COUNTA(S34:U34)=0,"",COUNTIF(S34:U34,"0")/COUNTA(S34:U34)) | X34: N5
A35: 33 | B35: =RAND() -> 0.96870606 | C35: あね | D35: 姉 | J35: =HYPERLINK(K35,"➸") -> ➸ | K35: =词典存放目录!$A$1&L35&M35 -> F:\《自创文法查阅Excel》4.1备份\《B词汇·红宝书》\红宝书15版图片\33-あね【姉】.jpg | L35: \红宝书15版图片\ | M35: 33-あね【姉】.jpg | N35: =HYPERLINK(R35,"▶") -> ▶ | O35: \红宝书MP3分割\01 n5-あ ( | P35: 33 | Q35: ).mp3 | R35: =词典存放目录!$A$1&O35&P35&Q35 -> F:\《自创文法查阅Excel》4.1备份\《B词汇·红宝书》\红宝书MP3分割\01 n5-あ (33).mp3 | V35: =IF(COUNTA(S35:U35)=0,"",COUNTIF(S35:U35,"0")/COUNTA(S35:U35)) | X35: N5
A36: 34 | B36: =RAND() -> 0.23017633 | C36: あの | J36: =HYPERLINK(K36,"➸") -> ➸ | K36: =词典存放目录!$A$1&L36&M36 -> F:\《自创文法查阅Excel》4.1备份\《B词汇·红宝书》\红宝书15版图片\34-あの.jpg | L36: \红宝书15版图片\ | M36: 34-あの.jpg | N36: =HYPERLINK(R36,"▶") -> ▶ | O36: \红宝书MP3分割\01 n5-あ ( | P36: 34 | Q36: ).mp3 | R36: =词典存放目录!$A$1&O36&P36&Q36 -> F:\《自创文法查阅Excel》4.1备份\《B词汇·红宝书》\红宝书MP3分割\01 n5-あ (34).mp3 | V36: =IF(COUNTA(S36:U36)=0,"",COUNTIF(S36:U36,"0")/COUNTA(S36:U36)) | X36: N5
A37: 35 | B37: =RAND() -> 0.34425406 | C37: あの/あのう | J37: =HYPERLINK(K37,"➸") -> ➸ | K37: =词典存放目录!$A$1&L37&M37 -> F:\《自创文法查阅Excel》4.1备份\《B词汇·红宝书》\红宝书15版图片\35-あの·あのう.jpg | L37: \红宝书15版图片\ | M37: 35-あの·あのう.jpg | N37: =HYPERLINK(R37,"▶") -> ▶ | O37: \红宝书MP3分割\01 n5-あ ( | P37: 35 | Q37: ).mp3 | R37: =词典存放目录!$A$1&O37&P37&Q37 -> F:\《自创文法查阅Excel》4.1备份\《B词汇·红宝书》\红宝书MP3分割\01 n5-あ (35).mp3 | V37: =IF(COUNTA(S37:U37)=0,"",COUNTIF(S37:U37,"0")/COUNTA(S37:U37)) | X37: N5
A38: 36 | B38: =RAND() -> 0.066005774 | C38: あのよう | D38: あの様 | J38: =HYPERLINK(K38,"➸") -> ➸ | K38: =词典存放目录!$A$1&L38&M38 -> F:\《自创文法查阅Excel》4.1备份\《B词汇·红宝书》\红宝书15版图片\36-あのよう【あの様】.jpg | L38: \红宝书15版图片\ | M38: 36-あのよう【あの様】.jpg | N38: =HYPERLINK(R38,"▶") -> ▶ | O38: \红宝书MP3分割\01 n5-あ ( | P38: 36 | Q38: ).mp3 | R38: =词典存放目录!$A$1&O38&P38&Q38 -> F:\《自创文法查阅Excel》4.1备份\《B词汇·红宝书》\红宝书MP3分割\01 n5-あ (36).mp3 | V38: =IF(COUNTA(S38:U38)=0,"",COUNTIF(S38:U38,"0")/COUNTA(S38:U38)) | X38: N5
A39: 37 | B39: =RAND() -> 0.2883946 | C39: アパート | D39: apartment | J39: =HYPERLINK(K39,"➸") -> ➸ | K39: =词典存放目录!$A$1&L39&M39 -> F:\《自创文法查阅Excel》4.1备份\《B词汇·红宝书》\红宝书15版图片\37-アパート【apartment】.jpg | L39: \红宝书15版图片\ | M39: 37-アパート【apartment】.jpg | N39: =HYPERLINK(R39,"▶") -> ▶ | O39: \红宝书MP3分割\01 n5-あ ( | P39: 37 | Q39: ).mp3 | R39: =词典存放目录!$A$1&O39&P39&Q39 -> F:\《自创文法查阅Excel》4.1备份\《B词汇·红宝书》\红宝书MP3分割\01 n5-あ (37).mp3 | V39: =IF(COUNTA(S39:U39)=0,"",COUNTIF(S39:U39,"0")/COUNTA(S39:U39)) | X39: N5
A40: 38 | B40: =RAND() -> 0.67720955 | C40: あびる | D40: 浴びる | J40: =HYPERLINK(K40,"➸") -> ➸ | K40: =词典存放目录!$A$1&L40&M40 -> F:\《自创文法查阅Excel》4.1备份\《B词汇·红宝书》\红宝书15版图片\38-あびる【浴びる】.jpg | L40: \红宝书15版图片\ | M40: 38-あびる【浴びる】.jpg | N40: =HYPERLINK(R40,"▶") -> ▶ | O40: \红宝书MP3分割\01 n5-あ ( | P40: 38 | Q40: ).mp3 | R40: =词典存放目录!$A$1&O40&P40&Q40 -> F:\《自创文法查阅Excel》4.1备份\《B词汇·红宝书》\红宝书MP3分割\01 n5-あ (38).mp3 | V40: =IF(COUNTA(S40:U40)=0,"",COUNTIF(S40:U40,"0")/COUNTA(S40:U40)) | X40: N5
A41: 39 | B41: =RAND() -> 0.81600511 | C41: あぶない | D41: 危ない | J41: =HYPERLINK(K41,"➸") -> ➸ | K41: =词典存放目录!$A$1&L41&M41 -> F:\《自创文法查阅Excel》4.1备份\《B词汇·红宝书》\红宝书15版图片\39-あぶない【危ない】.jpg | L41: \红宝书15版图片\ | M41: 39-あぶない【危ない】.jpg | N41: =HYPERLINK(R41,"▶") -> ▶ | O41: \红宝书MP3分割\01 n5-あ ( | P41: 39 | Q41: ).mp3 | R41: =词典存放目录!$A$1&O41&P41&Q41 -> F:\《自创文法查阅Excel》4.1备份\《B词汇·红宝书》\红宝书MP3分割\01 n5-あ (39).mp3 | V41: =IF(COUNTA(S41:U41)=0,"",COUNTIF(S41:U41,"0")/COUNTA(S41:U41)) | X41: N5
A42: 40 | B42: =RAND() -> 0.48341061 | C42: あまい | D42: 甘い | E42: A1 | J42: =HYPERLINK(K42,"➸") -> ➸ | K42: =词典存放目录!$A$1&L42&M42 -> F:\《自创文法查阅Excel》4.1备份\《B词汇·红宝书》\红宝书15版图片\40-あまい【甘い】.jpg | L42: \红宝书15版图片\ | M42: 40-あまい【甘い】.jpg | N42: =HYPERLINK(R42,"▶") -> ▶ | O42: \红宝书MP3分割\01 n5-あ ( | P42: 40 | Q42: ).mp3 | R42: =词典存放目录!$A$1&O42&P42&Q42 -> F:\《自创文法查阅Excel》4.1备份\《B词汇·红宝书》\红宝书MP3分割\01 n5-あ (40).mp3 | V42: =IF(COUNTA(S42:U42)=0,"",COUNTIF(S42:U42,"0")/COUNTA(S42:U42)) | X42: N5
A43: 41 | B43: =RAND() -> 0.87643538 | C43: あまり | D43: 余り | G43: AV | I43: り | J43: =HYPERLINK(K43,"➸") -> ➸ | K43: =词典存放目录!$A$1&L43&M43 -> F:\《自创文法查阅Excel》4.1备份\《B词汇·红宝书》\红宝书15版图片\41-あまり【余り】.jpg | L43: \红宝书15版图片\ | M43: 41-あまり【余り】.jpg | N43: =HYPERLINK(R43,"▶") -> ▶ | O43: \红宝书MP3分割\01 n5-あ ( | P43: 41 | Q43: ).mp3 | R43: =词典存放目录!$A$1&O43&P43&Q43 -> F:\《自创文法查阅Excel》4.1备份\《B词汇·红宝书》\红宝书MP3分割\01 n5-あ (41).mp3 | V43: =IF(COUNTA(S43:U43)=0,"",COUNTIF(S43:U43,"0")/COUNTA(S43:U43)) | X43: N5
A44: 42 | B44: =RAND() -> 0.84785802 | C44: あめ | D44: 雨 | J44: =HYPERLINK(K44,"➸") -> ➸ | K44: =词典存放目录!$A$1&L44&M44 -> F:\《自创文法查阅Excel》4.1备份\《B词汇·红宝书》\红宝书15版图片\42-あめ【雨】.jpg | L44: \红宝书15版图片\ | M44: 42-あめ【雨】.jpg | N44: =HYPERLINK(R44,"▶") -> ▶ | O44: \红宝书MP3分割\01 n5-あ ( | P44: 42 | Q44: ).mp3 | R44: =词典存放目录!$A$1&O44&P44&Q44 -> F:\《自创文法查阅Excel》4.1备份\《B词汇·红宝书》\红宝书MP3分割\01 n5-あ (42).mp3 | V44: =IF(COUNTA(S44:U44)=0,"",COUNTIF(S44:U44,"0")/COUNTA(S44:U44)) | X44: N5
A45: 43 | B45: =RAND() -> 0.64422299 | C45: あめ | D45: 飴 | J45: =HYPERLINK(K45,"➸") -> ➸ | K45: =词典存放目录!$A$1&L45&M45 -> F:\《自创文法查阅Excel》4.1备份\《B词汇·红宝书》\红宝书15版图片\43-あめ【飴】.jpg | L45: \红宝书15版图片\ | M45: 43-あめ【飴】.jpg | N45: =HYPERLINK(R45,"▶") -> ▶ | O45: \红宝书MP3分割\01 n5-あ ( | P45: 43 | Q45: ).mp3 | R45: =词典存放目录!$A$1&O45&P45&Q45 -> F:\《自创文法查阅Excel》4.1备份\《B词汇·红宝书》\红宝书MP3分割\01 n5-あ (43).mp3 | V45: =IF(COUNTA(S45:U45)=0,"",COUNTIF(S45:U45,"0")/COUNTA(S45:U45)) | X45: N5
A46: 44 | B46: =RAND() -> 0.29969288 | C46: あらう | D46: 洗う | J46: =HYPERLINK(K46,"➸") -> ➸ | K46: =词典存放目录!$A$1&L46&M46 -> F:\《自创文法查阅Excel》4.1备份\《B词汇·红宝书》\红宝书15版图片\44-あらう【洗う】.jpg | L46: \红宝书15版图片\ | M46: 44-あらう【洗う】.jpg | N46: =HYPERLINK(R46,"▶") -> ▶ | O46: \红宝书MP3分割\01 n5-あ ( | P46: 44 | Q46: ).mp3 | R46: =词典存放目录!$A$1&O46&P46&Q46 -> F:\《自创文法查阅Excel》4.1备份\《B词汇·红宝书》\红宝书MP3分割\01 n5-あ (44).mp3 | V46: =IF(COUNTA(S46:U46)=0,"",COUNTIF(S46:U46,"0")/COUNTA(S46:U46)) | X46: N5
A47: 45 | B47: =RAND() -> 0.57359571 | C47: ある | D47: 有る | J47: =HYPERLINK(K47,"➸") -> ➸ | K47: =词典存放目录!$A$1&L47&M47 -> F:\《自创文法查阅Excel》4.1备份\《B词汇·红宝书》\红宝书15版图片\45-ある【有る】.jpg | L47: \红宝书15版图片\ | M47: 45-ある【有る】.jpg | N47: =HYPERLINK(R47,"▶") -> ▶ | O47: \红宝书MP3分割\01 n5-あ ( | P47: 45 | Q47: ).mp3 | R47: =词典存放目录!$A$1&O47&P47&Q47 -> F:\《自创文法查阅Excel》4.1备份\《B词汇·红宝书》\红宝书MP3分割\01 n5-あ (45).mp3 | V47: =IF(COUNTA(S47:U47)=0,"",COUNTIF(S47:U47,"0")/COUNTA(S47:U47)) | X47: N5
A48: 46 | B48: =RAND() -> 0.73233632 | C48: あるく | D48: 歩く | J48: =HYPERLINK(K48,"➸") -> ➸ | K48: =词典存放目录!$A$1&L48&M48 -> F:\《自创文法查阅Excel》4.1备份\《B词汇·红宝书》\红宝书15版图片\46-あるく【歩く】.jpg | L48: \红宝书15版图片\ | M48: 46-あるく【歩く】.jpg | N48: =HYPERLINK(R48,"▶") -> ▶ | O48: \红宝书MP3分割\01 n5-あ ( | P48: 46 | Q48: ).mp3 | R48: =词典存放目录!$A$1&O48&P48&Q48 -> F:\《自创文法查阅Excel》4.1备份\《B词汇·红宝书》\红宝书MP3分割\01 n5-あ (46).mp3 | V48: =IF(COUNTA(S48:U48)=0,"",COUNTIF(S48:U48,"0")/COUNTA(S48:U48)) | X48: N5
A49: 47 | B49: =RAND() -> 0.63101067 | C49: アルバム | D49: album | J49: =HYPERLINK(K49,"➸") -> ➸ | K49: =词典存放目录!$A$1&L49&M49 -> F:\《自创文法查阅Excel》4.1备份\《B词汇·红宝书》\红宝书15版图片\47-アルバム【album】.jpg | L49: \红宝书15版图片\ | M49: 47-アルバム【album】.jpg | N49: =HYPERLINK(R49,"▶") -> ▶ | O49: \红宝书MP3分割\01 n5-あ ( | P49: 47 | Q49: ).mp3 | R49: =词典存放目录!$A$1&O49&P49&Q49 -> F:\《自创文法查阅Excel》4.1备份\《B词汇·红宝书》\红宝书MP3分割\01 n5-あ (47).mp3 | V49: =IF(COUNTA(S49:U49)=0,"",COUNTIF(S49:U49,"0")/COUNTA(S49:U49)) | X49: N5
A50: 48 | B50: =RAND() -> 0.94576734 | C50: あれ | J50: =HYPERLINK(K50,"➸") -> ➸ | K50: =词典存放目录!$A$1&L50&M50 -> F:\《自创文法查阅Excel》4.1备份\《B词汇·红宝书》\红宝书15版图片\48-あれ.jpg | L50: \红宝书15版图片\ | M50: 48-あれ.jpg | N50: =HYPERLINK(R50,"▶") -> ▶ | O50: \红宝书MP3分割\01 n5-あ ( | P50: 48 | Q50: ).mp3 | R50: =词典存放目录!$A$1&O50&P50&Q50 -> F:\《自创文法查阅Excel》4.1备份\《B词汇·红宝书》\红宝书MP3分割\01 n5-あ (48).mp3 | V50: =IF(COUNTA(S50:U50)=0,"",COUNTIF(S50:U50,"0")/COUNTA(S50:U50)) | X50: N5
A51: 49 | B51: =RAND() -> 0.46623643 | C51: あ | J51: =HYPERLINK(K51,"➸") -> ➸ | K51: =词典存放目录!$A$1&L51&M51 -> F:\《自创文法查阅Excel》4.1备份\《B词汇·红宝书》\红宝书15版图片\49-あ.jpg | L51: \红宝书15版图片\ | M51: 49-あ.jpg | N51: =HYPERLINK(R51,"▶") -> ▶ | O51: \红宝书MP3分割\01 n4-あ ( | P51: 1 | Q51: ).mp3 | R51: =词典存放目录!$A$1&O51&P51&Q51 -> F:\《自创文法查阅Excel》4.1备份\《B词汇·红宝书》\红宝书MP3分割\01 n4-あ (1).mp3 | V51: =IF(COUNTA(S51:U51)=0,"",COUNTIF(S51:U51,"0")/COUNTA(S51:U51)) | X51: N4
A52: 50 | B52: =RAND() -> 0.65696677 | C52: ああ | J52: =HYPERLINK(K52,"➸") -> ➸ | K52: =词典存放目录!$A$1&L52&M52 -> F:\《自创文法查阅Excel》4.1备份\《B词汇·红宝书》\红宝书15版图片\50-ああ.jpg | L52: \红宝书15版图片\ | M52: 50-ああ.jpg | N52: =HYPERLINK(R52,"▶") -> ▶ | O52: \红宝书MP3分割\01 n4-あ ( | P52: 2 | Q52: ).mp3 | R52: =词典存放目录!$A$1&O52&P52&Q52 -> F:\《自创文法查阅Excel》4.1备份\《B词汇·红宝书》\红宝书MP3分割\01 n4-あ (2).mp3 | V52: =IF(COUNTA(S52:U52)=0,"",COUNTIF(S52:U52,"0")/COUNTA(S52:U52)) | X52: N4
A53: 51 | B53: =RAND() -> 0.056769808 | C53: あい | D53: 愛 | J53: =HYPERLINK(K53,"➸") -> ➸ | K53: =词典存放目录!$A$1&L53&M53 -> F:\《自创文法查阅Excel》4.1备份\《B词汇·红宝书》\红宝书15版图片\51-あい【愛】.jpg | L53: \红宝书15版图片\ | M53: 51-あい【愛】.jpg | N53: =HYPERLINK(R53,"▶") -> ▶ | O53: \红宝书MP3分割\01 n4-あ ( | P53: 3 | Q53: ).mp3 | R53: =词典存放目录!$A$1&O53&P53&Q53 -> F:\《自创文法查阅Excel》4.1备份\《B词汇·红宝书》\红宝书MP3分割\01 n4-あ (3).mp3 | V53: =IF(COUNTA(S53:U53)=0,"",COUNTIF(S53:U53,"0")/COUNTA(S53:U53)) | X53: N4
A54: 52 | B54: =RAND() -> 0.44788219 | C54: あいけん | D54: 愛犬 | J54: =HYPERLINK(K54,"➸") -> ➸ | K54: =词典存放目录!$A$1&L54&M54 -> F:\《自创文法查阅Excel》4.1备份\《B词汇·红宝书》\红宝书15版图片\52-あいけん【愛犬】.jpg | L54: \红宝书15版图片\ | M54: 52-あいけん【愛犬】.jpg | N54: =HYPERLINK(R54,"▶") -> ▶ | O54: \红宝书MP3分割\01 n4-あ ( | P54: 4 | Q54: ).mp3 | R54: =词典存放目录!$A$1&O54&P54&Q54 -> F:\《自创文法查阅Excel》4.1备份\《B词汇·红宝书》\红宝书MP3分割\01 n4-あ (4).mp3 | V54: =IF(COUNTA(S54:U54)=0,"",COUNTIF(S54:U54,"0")/COUNTA(S54:U54)) | X54: N4
A55: 53 | B55: =RAND() -> 0.90819398 | C55: あいさつ | D55: 挨拶 | J55: =HYPERLINK(K55,"➸") -> ➸ | K55: =词典存放目录!$A$1&L55&M55 -> F:\《自创文法查阅Excel》4.1备份\《B词汇·红宝书》\红宝书15版图片\53-あいさつ【挨拶】.jpg | L55: \红宝书15版图片\ | M55: 53-あいさつ【挨拶】.jpg | N55: =HYPERLINK(R55,"▶") -> ▶ | O55: \红宝书MP3分割\01 n4-あ ( | P55: 5 | Q55: ).mp3 | R55: =词典存放目录!$A$1&O55&P55&Q55 -> F:\《自创文法查阅Excel》4.1备份\《B词汇·红宝书》\红宝书MP3分割\01 n4-あ (5).mp3 | V55: =IF(COUNTA(S55:U55)=0,"",COUNTIF(S55:U55,"0")/COUNTA(S55:U55)) | X55: N4
A56: 54 | B56: =RAND() -> 0.81011699 | C56: あいだ | D56: 間 | J56: =HYPERLINK(K56,"➸") -> ➸ | K56: =词典存放目录!$A$1&L56&M56 -> F:\《自创文法查阅Excel》4.1备份\《B词汇·红宝书》\红宝书15版图片\54-あいだ【間】.jpg | L56: \红宝书15版图片\ | M56: 54-あいだ【間】.jpg | N56: =HYPERLINK(R56,"▶") -> ▶ | O56: \红宝书MP3分割\01 n4-あ ( | P56: 6 | Q56: ).mp3 | R56: =词典存放目录!$A$1&O56&P56&Q56 -> F:\《自创文法查阅Excel》4.1备份\《B词汇·红宝书》\红宝书MP3分割\01 n4-あ (6).mp3 | V56: =IF(COUNTA(S56:U56)=0,"",COUNTIF(S56:U56,"0")/COUNTA(S56:U56)) | X56: N4
A57: 55 | B57: =RAND() -> 0.66542027 | C57: あう | D57: 合う | J57: =HYPERLINK(K57,"➸") -> ➸ | K57: =词典存放目录!$A$1&L57&M57 -> F:\《自创文法查阅Excel》4.1备份\《B词汇·红宝书》\红宝书15版图片\55-あう【合う】.jpg | L57: \红宝书15版图片\ | M57: 55-あう【合う】.jpg | N57: =HYPERLINK(R57,"▶") -> ▶ | O57: \红宝书MP3分割\01 n4-あ ( | P57: 7 | Q57: ).mp3 | R57: =词典存放目录!$A$1&O57&P57&Q57 -> F:\《自创文法查阅Excel》4.1备份\《B词汇·红宝书》\红宝书MP3分割\01 n4-あ (7).mp3 | V57: =IF(COUNTA(S57:U57)=0,"",COUNTIF(S57:U57,"0")/COUNTA(S57:U57)) | X57: N4
A58: 56 | B58: =RAND() -> 0.8128815 | C58: あう | D58: ～合う | J58: =HYPERLINK(K58,"➸") -> ➸ | K58: =词典存放目录!$A$1&L58&M58 -> F:\《自创文法查阅Excel》4.1备份\《B词汇·红宝书》\红宝书15版图片\56-あう【～合う】.jpg | L58: \红宝书15版图片\ | M58: 56-あう【～合う】.jpg | N58: =HYPERLINK(R58,"▶") -> ▶ | O58: \红宝书MP3分割\01 n4-あ ( | P58: 8 | Q58: ).mp3 | R58: =词典存放目录!$A$1&O58&P58&Q58 -> F:\《自创文法查阅Excel》4.1备份\《B词汇·红宝书》\红宝书MP3分割\01 n4-あ (8).mp3 | V58: =IF(COUNTA(S58:U58)=0,"",COUNTIF(S58:U58,"0")/COUNTA(S58:U58)) | X58: N4
A59: 57 | B59: =RAND() -> 0.59699051 | C59: あう | D59: 遭う | J59: =HYPERLINK(K59,"➸") -> ➸ | K59: =词典存放目录!$A$1&L59&M59 -> F:\《自创文法查阅Excel》4.1备份\《B词汇·红宝书》\红宝书15版图片\57-あう【遭う】.jpg | L59: \红宝书15版图片\ | M59: 57-あう【遭う】.jpg | N59: =HYPERLINK(R59,"▶") -> ▶ | O59: \红宝书MP3分割\01 n4-あ ( | P59: 9 | Q59: ).mp3 | R59: =词典存放目录!$A$1&O59&P59&Q59 -> F:\《自创文法查阅Excel》4.1备份\《B词汇·红宝书》\红宝书MP3分割\01 n4-あ (9).mp3 | V59: =IF(COUNTA(S59:U59)=0,"",COUNTIF(S59:U59,"0")/COUNTA(S59:U59)) | X59: N4
A60: 58 | B60: =RAND() -> 0.88489168 | C60: あおぞら | D60: 青空 | J60: =HYPERLINK(K60,"➸") -> ➸ | K60: =词典存放目录!$A$1&L60&M60 -> F:\《自创文法查阅Excel》4.1备份\《B词汇·红宝书》\红宝书15版图片\58-あおぞら【青空】.jpg | L60: \红宝书15版图片\ | M60: 58-あおぞら【青空】.jpg | N60: =HYPERLINK(R60,"▶") -> ▶ | O60: \红宝书MP3分割\01 n4-あ ( | P60: 10 | Q60: ).mp3 | R60: =词典存放目录!$A$1&O60&P60&Q60 -> F:\《自创文法查阅Excel》4.1备份\《B词汇·红宝书》\红宝书MP3分割\01 n4-あ (10).mp3 | V60: =IF(COUNTA(S60:U60)=0,"",COUNTIF(S60:U60,"0")/COUNTA(S60:U60)) | X60: N4
A61: 59 | B61: =RAND() -> 0.66745819 | C61: あかじ | D61: 赤字 | J61: =HYPERLINK(K61,"➸") -> ➸ | K61: =词典存放目录!$A$1&L61&M61 -> F:\《自创文法查阅Excel》4.1备份\《B词汇·红宝书》\红宝书15版图片\59-あかじ【赤字】.jpg | L61: \红宝书15版图片\ | M61: 59-あかじ【赤字】.jpg | N61: =HYPERLINK(R61,"▶") -> ▶ | O61: \红宝书MP3分割\01 n4-あ ( | P61: 11 | Q61: ).mp3 | R61: =词典存放目录!$A$1&O61&P61&Q61 -> F:\《自创文法查阅Excel》4.1备份\《B词汇·红宝书》\红宝书MP3分割\01 n4-あ (11).mp3 | V61: =IF(COUNTA(S61:U61)=0,"",COUNTIF(S61:U61,"0")/COUNTA(S61:U61)) | X61: N4
A62: 60 | B62: =RAND() -> 0.33983698 | C62: あかちゃん | D62: 赤ちゃん | J62: =HYPERLINK(K62,"➸") -> ➸ | K62: =词典存放目录!$A$1&L62&M62 -> F:\《自创文法查阅Excel》4.1备份\《B词汇·红宝书》\红宝书15版图片\60-あかちゃん【赤ちゃん】.jpg | L62: \红宝书15版图片\ | M62: 60-あかちゃん【赤ちゃん】.jpg | N62: =HYPERLINK(R62,"▶") -> ▶ | O62: \红宝书MP3分割\01 n4-あ ( | P62: 12 | Q62: ).mp3 | R62: =词典存放目录!$A$1&O62&P62&Q62 -> F:\《自创文法查阅Excel》4.1备份\《B词汇·红宝书》\红宝书MP3分割\01 n4-あ (12).mp3 | V62: =IF(COUNTA(S62:U62)=0,"",COUNTIF(S62:U62,"0")/COUNTA(S62:U62)) | X62: N4
A63: 61 | B63: =RAND() -> 0.90884074 | C63: あがる | D63: 上る | J63: =HYPERLINK(K63,"➸") -> ➸ | K63: =词典存放目录!$A$1&L63&M63 -> F:\《自创文法查阅Excel》4.1备份\《B词汇·红宝书》\红宝书15版图片\61-あがる【上る】.jpg | L63: \红宝书15版图片\ | M63: 61-あがる【上る】.jpg | N63: =HYPERLINK(R63,"▶") -> ▶ | O63: \红宝书MP3分割\01 n4-あ ( | P63: 13 | Q63: ).mp3 | R63: =词典存放目录!$A$1&O63&P63&Q63 -> F:\《自创文法查阅Excel》4.1备份\《B词汇·红宝书》\红宝书MP3分割\01 n4-あ (13).mp3 | V63: =IF(COUNTA(S63:U63)=0,"",COUNTIF(S63:U63,"0")/COUNTA(S63:U63)) | X63: N4
A64: 62 | B64: =RAND() -> 0.62592083 | C64: あかんぼう | D64: 赤ん坊 | J64: =HYPERLINK(K64,"➸") -> ➸ | K64: =词典存放目录!$A$1&L64&M64 -> F:\《自创文法查阅Excel》4.1备份\《B词汇·红宝书》\红宝书15版图片\62-あかんぼう【赤ん坊】.jpg | L64: \红宝书15版图片\ | M64: 62-あかんぼう【赤ん坊】.jpg | N64: =HYPERLINK(R64,"▶") -> ▶ | O64: \红宝书MP3分割\01 n4-あ ( | P64: 14 | Q64: ).mp3 | R64: =词典存放目录!$A$1&O64&P64&Q64 -> F:\《自创文法查阅Excel》4.1备份\《B词汇·红宝书》\红宝书MP3分割\01 n4-あ (14).mp3 | V64: =IF(COUNTA(S64:U64)=0,"",COUNTIF(S64:U64,"0")/COUNTA(S64:U64)) | X64: N4
... A68: 66 | B68: =RAND() -> 0.91002826 | C68: あこがれ | D68: 憧れ | J68: =HYPERLINK(K68,"➸") -> ➸ | K68: =词典存放目录!$A$1&L68&M68 -> F:\《自创文法查阅Excel》4.1备份\《B词汇·红宝书》\红宝书15版图片\66-あこがれ【憧れ】.jpg | L68: \红宝书15版图片\ | M68: 66-あこがれ【憧れ】.jpg | N68: =HYPERLINK(R68,"▶") -> ▶ | O68: \红宝书MP3分割\01 n4-あ ( | P68: 18 | Q68: ).mp3 | R68: =词典存放目录!$A$1&O68&P68&Q68 -> F:\《自创文法查阅Excel》4.1备份\《B词汇·红宝书》\红宝书MP3分割\01 n4-あ (18).mp3 | V68: =IF(COUNTA(S68:U68)=0,"",COUNTIF(S68:U68,"0")/COUNTA(S68:U68)) | X68: N4
A69: 67 | B69: =RAND() -> 0.30666913 | C69: あさい | D69: 浅い | E69: A1 | J69: =HYPERLINK(K69,"➸") -> ➸ | K69: =词典存放目录!$A$1&L69&M69 -> F:\《自创文法查阅Excel》4.1备份\《B词汇·红宝书》\红宝书15版图片\67-あさい【浅い】.jpg | L69: \红宝书15版图片\ | M69: 67-あさい【浅い】.jpg | N69: =HYPERLINK(R69,"▶") -> ▶ | O69: \红宝书MP3分割\01 n4-あ ( | P69: 19 | Q69: ).mp3 | R69: =词典存放目录!$A$1&O69&P69&Q69 -> F:\《自创文法查阅Excel》4.1备份\《B词汇·红宝书》\红宝书MP3分割\01 n4-あ (19).mp3 | V69: =IF(COUNTA(S69:U69)=0,"",COUNTIF(S69:U69,"0")/COUNTA(S69:U69)) | X69: N4
A70: 68 | B70: =RAND() -> 0.97226386 | C70: あじ | D70: 味 | J70: =HYPERLINK(K70,"➸") -> ➸ | K70: =词典存放目录!$A$1&L70&M70 -> F:\《自创文法查阅Excel》4.1备份\《B词汇·红宝书》\红宝书15版图片\68-あじ【味】.jpg | L70: \红宝书15版图片\ | M70: 68-あじ【味】.jpg | N70: =HYPERLINK(R70,"▶") -> ▶ | O70: \红宝书MP3分割\01 n4-あ ( | P70: 20 | Q70: ).mp3 | R70: =词典存放目录!$A$1&O70&P70&Q70 -> F:\《自创文法查阅Excel》4.1备份\《B词汇·红宝书》\红宝书MP3分割\01 n4-あ (20).mp3 | V70: =IF(COUNTA(S70:U70)=0,"",COUNTIF(S70:U70,"0")/COUNTA(S70:U70)) | X70: N4
A71: 69 | B71: =RAND() -> 0.98372225 | C71: アジア | D71: Asia | J71: =HYPERLINK(K71,"➸") -> ➸ | K71: =词典存放目录!$A$1&L71&M71 -> F:\《自创文法查阅Excel》4.1备份\《B词汇·红宝书》\红宝书15版图片\69-アジア【Asia】.jpg | L71: \红宝书15版图片\ | M71: 69-アジア【Asia】.jpg | N71: =HYPERLINK(R71,"▶") -> ▶ | O71: \红宝书MP3分割\01 n4-あ ( | P71: 21 | Q71: ).mp3 | R71: =词典存放目录!$A$1&O71&P71&Q71 -> F:\《自创文法查阅Excel》4.1备份\《B词汇·红宝书》\红宝书MP3分割\01 n4-あ (21).mp3 | V71: =IF(COUNTA(S71:U71)=0,"",COUNTIF(S71:U71,"0")/COUNTA(S71:U71)) | X71: N4
A72: 70 | B72: =RAND() -> 0.30629494 | C72: あそび | D72: 遊び | J72: =HYPERLINK(K72,"➸") -> ➸ | K72: =词典存放目录!$A$1&L72&M72 -> F:\《自创文法查阅Excel》4.1备份\《B词汇·红宝书》\红宝书15版图片\70-あそび【遊び】.jpg | L72: \红宝书15版图片\ | M72: 70-あそび【遊び】.jpg | N72: =HYPERLINK(R72,"▶") -> ▶ | O72: \红宝书MP3分割\01 n4-あ ( | P72: 22 | Q72: ).mp3 | R72: =词典存放目录!$A$1&O72&P72&Q72 -> F:\《自创文法查阅Excel》4.1备份\《B词汇·红宝书》\红宝书MP3分割\01 n4-あ (22).mp3 | V72: =IF(COUNTA(S72:U72)=0,"",COUNTIF(S72:U72,"0")/COUNTA(S72:U72)) | X72: N4
A73: 71 | B73: =RAND() -> 0.5782958 | C73: あたえる | D73: 与える | J73: =HYPERLINK(K73,"➸") -> ➸ | K73: =词典存放目录!$A$1&L73&M73 -> F:\《自创文法查阅Excel》4.1备份\《B词汇·红宝书》\红宝书15版图片\71-あたえる【与える】.jpg | L73: \红宝书15版图片\ | M73: 71-あたえる【与える】.jpg | N73: =HYPERLINK(R73,"▶") -> ▶ | O73: \红宝书MP3分割\01 n4-あ ( | P73: 23 | Q73: ).mp3 | R73: =词典存放目录!$A$1&O73&P73&Q73 -> F:\《自创文法查阅Excel》4.1备份\《B词汇·红宝书》\红宝书MP3分割\01 n4-あ (23).mp3 | V73: =IF(COUNTA(S73:U73)=0,"",COUNTIF(S73:U73,"0")/COUNTA(S73:U73)) | X73: N4
A74: 72 | B74: =RAND() -> 0.59728797 | C74: あたためる | D74: 温める/暖める | J74: =HYPERLINK(K74,"➸") -> ➸ | K74: =词典存放目录!$A$1&L74&M74 -> F:\《自创文法查阅Excel》4.1备份\《B词汇·红宝书》\红宝书15版图片\72-あたためる【温める·暖める】.jpg | L74: \红宝书15版图片\ | M74: 72-あたためる【温める·暖める】.jpg | N74: =HYPERLINK(R74,"▶") -> ▶ | O74: \红宝书MP3分割\01 n4-あ ( | P74: 24 | Q74: ).mp3 | R74: =词典存放目录!$A$1&O74&P74&Q74 -> F:\《自创文法查阅Excel》4.1备份\《B词汇·红宝书》\红宝书MP3分割\01 n4-あ (24).mp3 | V74: =IF(COUNTA(S74:U74)=0,"",COUNTIF(S74:U74,"0")/COUNTA(S74:U74)) | X74: N4
A75: 73 | B75: =RAND() -> 0.6308535 | C75: あたり | D75: 辺り | J75: =HYPERLINK(K75,"➸") -> ➸ | K75: =词典存放目录!$A$1&L75&M75 -> F:\《自创文法查阅Excel》4.1备份\《B词汇·红宝书》\红宝书15版图片\73-あたり【辺り】.jpg | L75: \红宝书15版图片\ | M75: 73-あたり【辺り】.jpg | N75: =HYPERLINK(R75,"▶") -> ▶ | O75: \红宝书MP3分割\01 n4-あ ( | P75: 25 | Q75: ).mp3 | R75: =词典存放目录!$A$1&O75&P75&Q75 -> F:\《自创文法查阅Excel》4.1备份\《B词汇·红宝书》\红宝书MP3分割\01 n4-あ (25).mp3 | V75: =IF(COUNTA(S75:U75)=0,"",COUNTIF(S75:U75,"0")/COUNTA(S75:U75)) | X75: N4
A76: 74 | B76: =RAND() -> 0.2835443 | C76: あたる | D76: 当たる | J76: =HYPERLINK(K76,"➸") -> ➸ | K76: =词典存放目录!$A$1&L76&M76 -> F:\《自创文法查阅Excel》4.1备份\《B词汇·红宝书》\红宝书15版图片\74-あたる【当たる】.jpg | L76: \红宝书15版图片\ | M76: 74-あたる【当たる】.jpg | N76: =HYPERLINK(R76,"▶") -> ▶ | O76: \红宝书MP3分割\01 n4-あ ( | P76: 26 | Q76: ).mp3 | R76: =词典存放目录!$A$1&O76&P76&Q76 -> F:\《自创文法查阅Excel》4.1备份\《B词汇·红宝书》\红宝书MP3分割\01 n4-あ (26).mp3 | V76: =IF(COUNTA(S76:U76)=0,"",COUNTIF(S76:U76,"0")/COUNTA(S76:U76)) | X76: N4
A77: 75 | B77: =RAND() -> 0.67535427 | C77: あちこち | J77: =HYPERLINK(K77,"➸") -> ➸ | K77: =词典存放目录!$A$1&L77&M77 -> F:\《自创文法查阅Excel》4.1备份\《B词汇·红宝书》\红宝书15版图片\75-あちこち.jpg | L77: \红宝书15版图片\ | M77: 75-あちこち.jpg | N77: =HYPERLINK(R77,"▶") -> ▶ | O77: \红宝书MP3分割\01 n4-あ ( | P77: 27 | Q77: ).mp3 | R77: =词典存放目录!$A$1&O77&P77&Q77 -> F:\《自创文法查阅Excel》4.1备份\《B词汇·红宝书》\红宝书MP3分割\01 n4-あ (27).mp3 | V77: =IF(COUNTA(S77:U77)=0,"",COUNTIF(S77:U77,"0")/COUNTA(S77:U77)) | X77: N4
A78: 76 | B78: =RAND() -> 0.21104696 | C78: あちらこちら | G78: AV | H78: D | J78: =HYPERLINK(K78,"➸") -> ➸ | K78: =词典存放目录!$A$1&L78&M78 -> F:\《自创文法查阅Excel》4.1备份\《B词汇·红宝书》\红宝书15版图片\76-あちらこちら.jpg | L78: \红宝书15版图片\ | M78: 76-あちらこちら.jpg | N78: =HYPERLINK(R78,"▶") -> ▶ | O78: \红宝书MP3分割\01 n4-あ ( | P78: 28 | Q78: ).mp3 | R78: =词典存放目录!$A$1&O78&P78&Q78 -> F:\《自创文法查阅Excel》4.1备份\《B词汇·红宝书》\红宝书MP3分割\01 n4-あ (28).mp3 | V78: =IF(COUNTA(S78:U78)=0,"",COUNTIF(S78:U78,"0")/COUNTA(S78:U78)) | X78: N4
A79: 79 | B79: =RAND() -> 0.661639 | C79: あっちこっち | G79: AV | H79: D | J79: =HYPERLINK(K79,"➸") -> ➸ | K79: =词典存放目录!$A$1&L79&M79 -> F:\《自创文法查阅Excel》4.1备份\《B词汇·红宝书》\红宝书15版图片\79-あっちこっち.jpg | L79: \红宝书15版图片\ | M79: 79-あっちこっち.jpg | N79: =HYPERLINK(R79,"▶") -> ▶ | O79: \红宝书MP3分割\01 n4-あ ( | P79: 31 | Q79: ).mp3 | R79: =词典存放目录!$A$1&O79&P79&Q79 -> F:\《自创文法查阅Excel》4.1备份\《B词汇·红宝书》\红宝书MP3分割\01 n4-あ (31).mp3 | V79: =IF(COUNTA(S79:U79)=0,"",COUNTIF(S79:U79,"0")/COUNTA(S79:U79)) | X79: N4
A80: 80 | B80: =RAND() -> 0.09388236 | C80: あつまる | D80: 集まる | J80: =HYPERLINK(K80,"➸") -> ➸ | K80: =词典存放目录!$A$1&L80&M80 -> F:\《自创文法查阅Excel》4.1备份\《B词汇·红宝书》\红宝书15版图片\80-あつまる【集まる】.jpg | L80: \红宝书15版图片\ | M80: 80-あつまる【集まる】.jpg | N80: =HYPERLINK(R80,"▶") -> ▶ | O80: \红宝书MP3分割\01 n4-あ ( | P80: 32 | Q80: ).mp3 | R80: =词典存放目录!$A$1&O80&P80&Q80 -> F:\《自创文法查阅Excel》4.1备份\《B词汇·红宝书》\红宝书MP3分割\01 n4-あ (32).mp3 | V80: =IF(COUNTA(S80:U80)=0,"",COUNTIF(S80:U80,"0")/COUNTA(S80:U80)) | X80: N4
A81: 81 | B81: =RAND() -> 0.2931946 | C81: あつめる | D81: 集める | J81: =HYPERLINK(K81,"➸") -> ➸ | K81: =词典存放目录!$A$1&L81&M81 -> F:\《自创文法查阅Excel》4.1备份\《B词汇·红宝书》\红宝书15版图片\81-あつめる【集める】.jpg | L81: \红宝书15版图片\ | M81: 81-あつめる【集める】.jpg | N81: =HYPERLINK(R81,"▶") -> ▶ | O81: \红宝书MP3分割\01 n4-あ ( | P81: 33 | Q81: ).mp3 | R81: =词典存放目录!$A$1&O81&P81&Q81 -> F:\《自创文法查阅Excel》4.1备份\《B词汇·红宝书》\红宝书MP3分割\01 n4-あ (33).mp3 | V81: =IF(COUNTA(S81:U81)=0,"",COUNTIF(S81:U81,"0")/COUNTA(S81:U81)) | X81: N4
A82: 82 | B82: =RAND() -> 0.90776304 | C82: あてる | D82: 当てる | J82: =HYPERLINK(K82,"➸") -> ➸ | K82: =词典存放目录!$A$1&L82&M82 -> F:\《自创文法查阅Excel》4.1备份\《B词汇·红宝书》\红宝书15版图片\82-あてる【当てる】.jpg | L82: \红宝书15版图片\ | M82: 82-あてる【当てる】.jpg | N82: =HYPERLINK(R82,"▶") -> ▶ | O82: \红宝书MP3分割\01 n4-あ ( | P82: 34 | Q82: ).mp3 | R82: =词典存放目录!$A$1&O82&P82&Q82 -> F:\《自创文法查阅Excel》4.1备份\《B词汇·红宝书》\红宝书MP3分割\01 n4-あ (34).mp3 | V82: =IF(COUNTA(S82:U82)=0,"",COUNTIF(S82:U82,"0")/COUNTA(S82:U82)) | X82: N4
A83: 83 | B83: =RAND() -> 0.57798012 | C83: アドレス | D83: address | J83: =HYPERLINK(K83,"➸") -> ➸ | K83: =词典存放目录!$A$1&L83&M83 -> F:\《自创文法查阅Excel》4.1备份\《B词汇·红宝书》\红宝书15版图片\83-アドレス【address】.jpg | L83: \红宝书15版图片\ | M83: 83-アドレス【address】.jpg | N83: =HYPERLINK(R83,"▶") -> ▶ | O83: \红宝书MP3分割\01 n4-あ ( | P83: 35 | Q83: ).mp3 | R83: =词典存放目录!$A$1&O83&P83&Q83 -> F:\《自创文法查阅Excel》4.1备份\《B词汇·红宝书》\红宝书MP3分割\01 n4-あ (35).mp3 | V83: =IF(COUNTA(S83:U83)=0,"",COUNTIF(S83:U83,"0")/COUNTA(S83:U83)) | X83: N4
A84: 84 | B84: =RAND() -> 0.76398134 | C84: アナウンサー | D84: announcer | J84: =HYPERLINK(K84,"➸") -> ➸ | K84: =词典存放目录!$A$1&L84&M84 -> F:\《自创文法查阅Excel》4.1备份\《B词汇·红宝书》\红宝书15版图片\84-アナウンサー【announcer】.jpg | L84: \红宝书15版图片\ | M84: 84-アナウンサー【announcer】.jpg | N84: =HYPERLINK(R84,"▶") -> ▶ | O84: \红宝书MP3分割\01 n4-あ ( | P84: 36 | Q84: ).mp3 | R84: =词典存放目录!$A$1&O84&P84&Q84 -> F:\《自创文法查阅Excel》4.1备份\《B词汇·红宝书》\红宝书MP3分割\01 n4-あ (36).mp3 | V84: =IF(COUNTA(S84:U84)=0,"",COUNTIF(S84:U84,"0")/COUNTA(S84:U84)) | X84: N4
A85: 85 | B85: =RAND() -> 0.52074559 | C85: アニメ | D85: animation | J85: =HYPERLINK(K85,"➸") -> ➸ | K85: =词典存放目录!$A$1&L85&M85 -> F:\《自创文法查阅Excel》4.1备份\《B词汇·红宝书》\红宝书15版图片\85-アニメ【animation】.jpg | L85: \红宝书15版图片\ | M85: 85-アニメ【animation】.jpg | N85: =HYPERLINK(R85,"▶") -> ▶ | O85: \红宝书MP3分割\01 n4-あ ( | P85: 37 | Q85: ).mp3 | R85: =词典存放目录!$A$1&O85&P85&Q85 -> F:\《自创文法查阅Excel》4.1备份\《B词汇·红宝书》\红宝书MP3分割\01 n4-あ (37).mp3 | V85: =IF(COUNTA(S85:U85)=0,"",COUNTIF(S85:U85,"0")/COUNTA(S85:U85)) | X85: N4
A86: 86 | B86: =RAND() -> 0.95994806 | C86: あのね | J86: =HYPERLINK(K86,"➸") -> ➸ | K86: =词典存放目录!$A$1&L86&M86 -> F:\《自创文法查阅Excel》4.1备份\《B词汇·红宝书》\红宝书15版图片\86-あのね.jpg | L86: \红宝书15版图片\ | M86: 86-あのね.jpg | N86: =HYPERLINK(R86,"▶") -> ▶ | O86: \红宝书MP3分割\01 n4-あ ( | P86: 38 | Q86: ).mp3 | R86: =词典存放目录!$A$1&O86&P86&Q86 -> F:\《自创文法查阅Excel》4.1备份\《B词汇·红宝书》\红宝书MP3分割\01 n4-あ (38).mp3 | V86: =IF(COUNTA(S86:U86)=0,"",COUNTIF(S86:U86,"0")/COUNTA(S86:U86)) | X86: N4
A87: 88 | B87: =RAND() -> 0.69232443 | C87: あぶら | D87: 油 | J87: =HYPERLINK(K87,"➸") -> ➸ | K87: =词典存放目录!$A$1&L87&M87 -> F:\《自创文法查阅Excel》4.1备份\《B词汇·红宝书》\红宝书15版图片\88-あぶら【油】.jpg | L87: \红宝书15版图片\ | M87: 88-あぶら【油】.jpg | N87: =HYPERLINK(R87,"▶") -> ▶ | O87: \红宝书MP3分割\01 n4-あ ( | P87: 40 | Q87: ).mp3 | R87: =词典存放目录!$A$1&O87&P87&Q87 -> F:\《自创文法查阅Excel》4.1备份\《B词汇·红宝书》\红宝书MP3分割\01 n4-あ (40).mp3 | V87: =IF(COUNTA(S87:U87)=0,"",COUNTIF(S87:U87,"0")/COUNTA(S87:U87)) | X87: N4
A88: 89 | B88: =RAND() -> 0.3395918 | C88: アフリカ | D88: Africa | J88: =HYPERLINK(K88,"➸") -> ➸ | K88: =词典存放目录!$A$1&L88&M88 -> F:\《自创文法查阅Excel》4.1备份\《B词汇·红宝书》\红宝书15版图片\89-アフリカ【Africa】.jpg | L88: \红宝书15版图片\ | M88: 89-アフリカ【Africa】.jpg | N88: =HYPERLINK(R88,"▶") -> ▶ | O88: \红宝书MP3分割\01 n4-あ ( | P88: 41 | Q88: ).mp3 | R88: =词典存放目录!$A$1&O88&P88&Q88 -> F:\《自创文法查阅Excel》4.1备份\《B词汇·红宝书》\红宝书MP3分割\01 n4-あ (41).mp3 | V88: =IF(COUNTA(S88:U88)=0,"",COUNTIF(S88:U88,"0")/COUNTA(S88:U88)) | X88: N4
A89: 90 | B89: =RAND() -> 0.98594701 | C89: あみもの | D89: 編み物 | J89: =HYPERLINK(K89,"➸") -> ➸ | K89: =词典存放目录!$A$1&L89&M89 -> F:\《自创文法查阅Excel》4.1备份\《B词汇·红宝书》\红宝书15版图片\90-あみもの【編み物】.jpg | L89: \红宝书15版图片\ | M89: 90-あみもの【編み物】.jpg | N89: =HYPERLINK(R89,"▶") -> ▶ | O89: \红宝书MP3分割\01 n4-あ ( | P89: 42 | Q89: ).mp3 | R89: =词典存放目录!$A$1&O89&P89&Q89 -> F:\《自创文法查阅Excel》4.1备份\《B词汇·红宝书》\红宝书MP3分割\01 n4-あ (42).mp3 | V89: =IF(COUNTA(S89:U89)=0,"",COUNTIF(S89:U89,"0")/COUNTA(S89:U89)) | X89: N4
A90: 91 | B90: =RAND() -> 0.2469024 | C90: あむ | D90: 編む | J90: =HYPERLINK(K90,"➸") -> ➸ | K90: =词典存放目录!$A$1&L90&M90 -> F:\《自创文法查阅Excel》4.1备份\《B词汇·红宝书》\红宝书15版图片\91-あむ【編む】.jpg | L90: \红宝书15版图片\ | M90: 91-あむ【編む】.jpg | N90: =HYPERLINK(R90,"▶") -> ▶ | O90: \红宝书MP3分割\01 n4-あ ( | P90: 43 | Q90: ).mp3 | R90: =词典存放目录!$A$1&O90&P90&Q90 -> F:\《自创文法查阅Excel》4.1备份\《B词汇·红宝书》\红宝书MP3分割\01 n4-あ (43).mp3 | V90: =IF(COUNTA(S90:U90)=0,"",COUNTIF(S90:U90,"0")/COUNTA(S90:U90)) | X90: N4
A91: 92 | B91: =RAND() -> 0.037711326 | C91: アメリカ | D91: America | J91: =HYPERLINK(K91,"➸") -> ➸ | K91: =词典存放目录!$A$1&L91&M91 -> F:\《自创文法查阅Excel》4.1备份\《B词汇·红宝书》\红宝书15版图片\92-アメリカ【America】.jpg | L91: \红宝书15版图片\ | M91: 92-アメリカ【America】.jpg | N91: =HYPERLINK(R91,"▶") -> ▶ | O91: \红宝书MP3分割\01 n4-あ ( | P91: 44 | Q91: ).mp3 | R91: =词典存放目录!$A$1&O91&P91&Q91 -> F:\《自创文法查阅Excel》4.1备份\《B词汇·红宝书》\红宝书MP3分割\01 n4-あ (44).mp3 | V91: =IF(COUNTA(S91:U91)=0,"",COUNTIF(S91:U91,"0")/COUNTA(S91:U91)) | X91: N4
A92: 93 | B92: =RAND() -> 0.63693754 | C92: あやまる | D92: 謝る | J92: =HYPERLINK(K92,"➸") -> ➸ | K92: =词典存放目录!$A$1&L92&M92 -> F:\《自创文法查阅Excel》4.1备份\《B词汇·红宝书》\红宝书15版图片\93-あやまる【謝る】.jpg | L92: \红宝书15版图片\ | M92: 93-あやまる【謝る】.jpg | N92: =HYPERLINK(R92,"▶") -> ▶ | O92: \红宝书MP3分割\01 n4-あ ( | P92: 45 | Q92: ).mp3 | R92: =词典存放目录!$A$1&O92&P92&Q92 -> F:\《自创文法查阅Excel》4.1备份\《B词汇·红宝书》\红宝书MP3分割\01 n4-あ (45).mp3 | V92: =IF(COUNTA(S92:U92)=0,"",COUNTIF(S92:U92,"0")/COUNTA(S92:U92)) | X92: N4
A93: 94 | B93: =RAND() -> 0.87027446 | C93: あら | J93: =HYPERLINK(K93,"➸") -> ➸ | K93: =词典存放目录!$A$1&L93&M93 -> F:\《自创文法查阅Excel》4.1备份\《B词汇·红宝书》\红宝书15版图片\94-あら.jpg | L93: \红宝书15版图片\ | M93: 94-あら.jpg | N93: =HYPERLINK(R93,"▶") -> ▶ | O93: \红宝书MP3分割\01 n4-あ ( | P93: 46 | Q93: ).mp3 | R93: =词典存放目录!$A$1&O93&P93&Q93 -> F:\《自创文法查阅Excel》4.1备份\《B词汇·红宝书》\红宝书MP3分割\01 n4-あ (46).mp3 | V93: =IF(COUNTA(S93:U93)=0,"",COUNTIF(S93:U93,"0")/COUNTA(S93:U93)) | X93: N4
A94: 95 | B94: =RAND() -> 0.91519932 | C94: アラーム | D94: alarm | J94: =HYPERLINK(K94,"➸") -> ➸ | K94: =词典存放目录!$A$1&L94&M94 -> F:\《自创文法查阅Excel》4.1备份\《B词汇·红宝书》\红宝书15版图片\95-アラーム【alarm】.jpg | L94: \红宝书15版图片\ | M94: 95-アラーム【alarm】.jpg | N94: =HYPERLINK(R94,"▶") -> ▶ | O94: \红宝书MP3分割\01 n4-あ ( | P94: 47 | Q94: ).mp3 | R94: =词典存放目录!$A$1&O94&P94&Q94 -> F:\《自创文法查阅Excel》4.1备份\《B词汇·红宝书》\红宝书MP3分割\01 n4-あ (47).mp3 | V94: =IF(COUNTA(S94:U94)=0,"",COUNTIF(S94:U94,"0")/COUNTA(S94:U94)) | X94: N4
A95: 96 | B95: =RAND() -> 0.85768316 | C95: あらわす | D95: 表す | J95: =HYPERLINK(K95,"➸") -> ➸ | K95: =词典存放目录!$A$1&L95&M95 -> F:\《自创文法查阅Excel》4.1备份\《B词汇·红宝书》\红宝书15版图片\96-あらわす【表す】.jpg | L95: \红宝书15版图片\ | M95: 96-あらわす【表す】.jpg | N95: =HYPERLINK(R95,"▶") -> ▶ | O95: \红宝书MP3分割\01 n4-あ ( | P95: 48 | Q95: ).mp3 | R95: =词典存放目录!$A$1&O95&P95&Q95 -> F:\《自创文法查阅Excel》4.1备份\《B词汇·红宝书》\红宝书MP3分割\01 n4-あ (48).mp3 | V95: =IF(COUNTA(S95:U95)=0,"",COUNTIF(S95:U95,"0")/COUNTA(S95:U95)) | X95: N4
A96: 97 | B96: =RAND() -> 0.52209681 | C96: ある | J96: =HYPERLINK(K96,"➸") -> ➸ | K96: =词典存放目录!$A$1&L96&M96 -> F:\《自创文法查阅Excel》4.1备份\《B词汇·红宝书》\红宝书15版图片\97-ある.jpg | L96: \红宝书15版图片\ | M96: 97-ある.jpg | N96: =HYPERLINK(R96,"▶") -> ▶ | O96: \红宝书MP3分割\01 n4-あ ( | P96: 49 | Q96: ).mp3 | R96: =词典存放目录!$A$1&O96&P96&Q96 -> F:\《自创文法查阅Excel》4.1备份\《B词汇·红宝书》\红宝书MP3分割\01 n4-あ (49).mp3 | V96: =IF(COUNTA(S96:U96)=0,"",COUNTIF(S96:U96,"0")/COUNTA(S96:U96)) | X96: N4
A97: 98 | B97: =RAND() -> 0.094233879 | C97: アルコール | D97: alcohol（荷） | J97: =HYPERLINK(K97,"➸") -> ➸ | K97: =词典存放目录!$A$1&L97&M97 -> F:\《自创文法查阅Excel》4.1备份\《B词汇·红宝书》\红宝书15版图片\98-アルコール【alcohol（荷）】.jpg | L97: \红宝书15版图片\ | M97: 98-アルコール【alcohol（荷）】.jpg | N97: =HYPERLINK(R97,"▶") -> ▶ | O97: \红宝书MP3分割\01 n4-あ ( | P97: 50 | Q97: ).mp3 | R97: =词典存放目录!$A$1&O97&P97&Q97 -> F:\《自创文法查阅Excel》4.1备份\《B词汇·红宝书》\红宝书MP3分割\01 n4-あ (50).mp3 | V97: =IF(COUNTA(S97:U97)=0,"",COUNTIF(S97:U97,"0")/COUNTA(S97:U97)) | X97: N4
A98: 99 | B98: =RAND() -> 0.93940572 | C98: アルバイト | D98: Arbeit（德） | J98: =HYPERLINK(K98,"➸") -> ➸ | K98: =词典存放目录!$A$1&L98&M98 -> F:\《自创文法查阅Excel》4.1备份\《B词汇·红宝书》\红宝书15版图片\99-アルバイト【Arbeit（德）】.jpg | L98: \红宝书15版图片\ | M98: 99-アルバイト【Arbeit（德）】.jpg | N98: =HYPERLINK(R98,"▶") -> ▶ | O98: \红宝书MP3分割\01 n4-あ ( | P98: 51 | Q98: ).mp3 | R98: =词典存放目录!$A$1&O98&P98&Q98 -> F:\《自创文法查阅Excel》4.1备份\《B词汇·红宝书》\红宝书MP3分割\01 n4-あ (51).mp3 | V98: =IF(COUNTA(S98:U98)=0,"",COUNTIF(S98:U98,"0")/COUNTA(S98:U98)) | X98: N4
A99: 100 | B99: =RAND() -> 0.68437358 | C99: あれ | J99: =HYPERLINK(K99,"➸") -> ➸ | K99: =词典存放目录!$A$1&L99&M99 -> F:\《自创文法查阅Excel》4.1备份\《B词汇·红宝书》\红宝书15版图片\100-あれ.jpg | L99: \红宝书15版图片\ | M99: 100-あれ.jpg | N99: =HYPERLINK(R99,"▶") -> ▶ | O99: \红宝书MP3分割\01 n4-あ ( | P99: 52 | Q99: ).mp3 | R99: =词典存放目录!$A$1&O99&P99&Q99 -> F:\《自创文法查阅Excel》4.1备份\《B词汇·红宝书》\红宝书MP3分割\01 n4-あ (52).mp3 | V99: =IF(COUNTA(S99:U99)=0,"",COUNTIF(S99:U99,"0")/COUNTA(S99:U99)) | X99: N4
A100: 101 | B100: =RAND() -> 0.14834735 | C100: あれえ | J100: =HYPERLINK(K100,"➸") -> ➸ | K100: =词典存放目录!$A$1&L100&M100 -> F:\《自创文法查阅Excel》4.1备份\《B词汇·红宝书》\红宝书15版图片\101-あれえ.jpg | L100: \红宝书15版图片\ | M100: 101-あれえ.jpg | N100: =HYPERLINK(R100,"▶") -> ▶ | O100: \红宝书MP3分割\01 n4-あ ( | P100: 53 | Q100: ).mp3 | R100: =词典存放目录!$A$1&O100&P100&Q100 -> F:\《自创文法查阅Excel》4.1备份\《B词汇·红宝书》\红宝书MP3分割\01 n4-あ (53).mp3 | V100: =IF(COUNTA(S100:U100)=0,"",COUNTIF(S100:U100,"0")/COUNTA(S100:U100)) | X100: N4
A101: 102 | B101: =RAND() -> 0.15067594 | C101: あれっ | J101: =HYPERLINK(K101,"➸") -> ➸ | K101: =词典存放目录!$A$1&L101&M101 -> F:\《自创文法查阅Excel》4.1备份\《B词汇·红宝书》\红宝书15版图片\102-あれっ.jpg | L101: \红宝书15版图片\ | M101: 102-あれっ.jpg | N101: =HYPERLINK(R101,"▶") -> ▶ | O101: \红宝书MP3分割\01 n4-あ ( | P101: 54 | Q101: ).mp3 | R101: =词典存放目录!$A$1&O101&P101&Q101 -> F:\《自创文法查阅Excel》4.1备份\《B词汇·红宝书》\红宝书MP3分割\01 n4-あ (54).mp3 | V101: =IF(COUNTA(S101:U101)=0,"",COUNTIF(S101:U101,"0")/COUNTA(S101:U101)) | X101: N4
A102: 103 | B102: =RAND() -> 0.46526231 | C102: あわい | D102: 淡い | E102: A1 | J102: =HYPERLINK(K102,"➸") -> ➸ | K102: =词典存放目录!$A$1&L102&M102 -> F:\《自创文法查阅Excel》4.1备份\《B词汇·红宝书》\红宝书15版图片\103-あわい【淡い】.jpg | L102: \红宝书15版图片\ | M102: 103-あわい【淡い】.jpg | N102: =HYPERLINK(R102,"▶") -> ▶ | O102: \红宝书MP3分割\01 n4-あ ( | P102: 55 | Q102: ).mp3 | R102: =词典存放目录!$A$1&O102&P102&Q102 -> F:\《自创文法查阅Excel》4.1备份\《B词汇·红宝书》\红宝书MP3分割\01 n4-あ (55).mp3 | V102: =IF(COUNTA(S102:U102)=0,"",COUNTIF(S102:U102,"0")/COUNTA(S102:U102)) | X102: N4
A103: 104 | B103: =RAND() -> 0.26686085 | C103: あんしん | D103: 安心 | J103: =HYPERLINK(K103,"➸") -> ➸ | K103: =词典存放目录!$A$1&L103&M103 -> F:\《自创文法查阅Excel》4.1备份\《B词汇·红宝书》\红宝书15版图片\104-あんしん【安心】.jpg | L103: \红宝书15版图片\ | M103: 104-あんしん【安心】.jpg | N103: =HYPERLINK(R103,"▶") -> ▶ | O103: \红宝书MP3分割\01 n4-あ ( | P103: 56 | Q103: ).mp3 | R103: =词典存放目录!$A$1&O103&P103&Q103 -> F:\《自创文法查阅Excel》4.1备份\《B词汇·红宝书》\红宝书MP3分割\01 n4-あ (56).mp3 | V103: =IF(COUNTA(S103:U103)=0,"",COUNTIF(S103:U103,"0")/COUNTA(S103:U103)) | X103: N4
...

Sheet 考前对策 · N2汉字（未完）
D1: =IF(A1<>"",A1&" "&"[["&B1&" "&C1&"]]","")
A2: 2288 | B2: きんえん | C2: 禁煙 | D2: =IF(A2<>"",A2&" "&"[["&B2&" "&C2&"]]","") -> 2288 [[きんえん 禁煙]] | E2: =IF(F2<>"",HYPERLINK(F2,"→"),"") -> → | F2: =IFERROR(VLOOKUP(A2,红宝书去重版!$A:$S,11,FALSE),"") -> F:\《自创文法查阅Excel》4.1备份\《B词汇·红宝书》\红宝书15版图片\2288-きんえん【禁煙】.jpg | G2: =IF(H2<>"",HYPERLINK(H2,"▶"),"") -> ▶ | H2: =IFERROR(VLOOKUP(A2,红宝书去重版!$A:$S,18,FALSE),"") -> F:\《自创文法查阅Excel》4.1备份\《B词汇·红宝书》\红宝书MP3分割\07 n3-き (85).mp3
A3: 2289 | B3: きんえんせき | C3: 禁煙席 | D3: =IF(A3<>"",A3&" "&"[["&B3&" "&C3&"]]","") -> 2289 [[きんえんせき 禁煙席]] | E3: =IF(F3<>"",HYPERLINK(F3,"→"),"") -> → | F3: =IFERROR(VLOOKUP(A3,红宝书去重版!$A:$S,11,FALSE),"") -> F:\《自创文法查阅Excel》4.1备份\《B词汇·红宝书》\红宝书15版图片\2289-きんえんせき【禁煙席】.jpg | G3: =IF(H3<>"",HYPERLINK(H3,"▶"),"") -> ▶ | H3: =IFERROR(VLOOKUP(A3,红宝书去重版!$A:$S,18,FALSE),"") -> F:\《自创文法查阅Excel》4.1备份\《B词汇·红宝书》\红宝书MP3分割\07 n3-き (86).mp3
A4: 2292 | B4: きんし | C4: 禁止 | D4: =IF(A4<>"",A4&" "&"[["&B4&" "&C4&"]]","") -> 2292 [[きんし 禁止]] | E4: =IF(F4<>"",HYPERLINK(F4,"→"),"") -> → | F4: =IFERROR(VLOOKUP(A4,红宝书去重版!$A:$S,11,FALSE),"") -> F:\《自创文法查阅Excel》4.1备份\《B词汇·红宝书》\红宝书15版图片\2292-きんし【禁止】.jpg | G4: =IF(H4<>"",HYPERLINK(H4,"▶"),"") -> ▶ | H4: =IFERROR(VLOOKUP(A4,红宝书去重版!$A:$S,18,FALSE),"") -> F:\《自创文法查阅Excel》4.1备份\《B词汇·红宝书》\红宝书MP3分割\07 n3-き (89).mp3
A5: 2386 | B5: きんじる | C5: 禁じる | D5: =IF(A5<>"",A5&" "&"[["&B5&" "&C5&"]]","") -> 2386 [[きんじる 禁じる]] | E5: =IF(F5<>"",HYPERLINK(F5,"→"),"") -> → | F5: =IFERROR(VLOOKUP(A5,红宝书去重版!$A:$S,11,FALSE),"") -> F:\《自创文法查阅Excel》4.1备份\《B词汇·红宝书》\红宝书15版图片\2386-きんじる【禁じる】.jpg | G5: =IF(H5<>"",HYPERLINK(H5,"▶"),"") -> ▶ | H5: =IFERROR(VLOOKUP(A5,红宝书去重版!$A:$S,18,FALSE),"") -> F:\《自创文法查阅Excel》4.1备份\《B词汇·红宝书》\红宝书MP3分割\07 n2-き (88).mp3
A6: 2558 | B6: きんもつ | C6: 禁物 | D6: =IF(A6<>"",A6&" "&"[["&B6&" "&C6&"]]","") -> 2558 [[きんもつ 禁物]] | E6: =IF(F6<>"",HYPERLINK(F6,"→"),"") -> → | F6: =IFERROR(VLOOKUP(A6,红宝书去重版!$A:$S,11,FALSE),"") -> F:\《自创文法查阅Excel》4.1备份\《B词汇·红宝书》\红宝书15版图片\2558-きんもつ【禁物】.jpg | G6: =IF(H6<>"",HYPERLINK(H6,"▶"),"") -> ▶ | H6: =IFERROR(VLOOKUP(A6,红宝书去重版!$A:$S,18,FALSE),"") -> F:\《自创文法查阅Excel》4.1备份\《B词汇·红宝书》\红宝书MP3分割\07 n1-き (169).mp3
D7: =IF(A7<>"",A7&" "&"[["&B7&" "&C7&"]]","") | E7: =IF(F7<>"",HYPERLINK(F7,"→"),"") | F7: =IFERROR(VLOOKUP(A7,红宝书去重版!$A:$S,11,FALSE),"") | G7: =IF(H7<>"",HYPERLINK(H7,"▶"),"") | H7: =IFERROR(VLOOKUP(A7,红宝书去重版!$A:$S,18,FALSE),"")
A8: 1013 | B8: えんとつ | C8: 煙突 | D8: =IF(A8<>"",A8&" "&"[["&B8&" "&C8&"]]","") -> 1013 [[えんとつ 煙突]] | E8: =IF(F8<>"",HYPERLINK(F8,"→"),"") -> → | F8: =IFERROR(VLOOKUP(A8,红宝书去重版!$A:$S,11,FALSE),"") -> F:\《自创文法查阅Excel》4.1备份\《B词汇·红宝书》\红宝书15版图片\1013-えんとつ【煙突】.jpg | G8: =IF(H8<>"",HYPERLINK(H8,"▶"),"") -> ▶ | H8: =IFERROR(VLOOKUP(A8,红宝书去重版!$A:$S,18,FALSE),"") -> F:\《自创文法查阅Excel》4.1备份\《B词汇·红宝书》\红宝书MP3分割\04 n2-え (19).mp3
A9: 2172 | B9: きつえん | C9: 喫煙 | D9: =IF(A9<>"",A9&" "&"[["&B9&" "&C9&"]]","") -> 2172 [[きつえん 喫煙]] | E9: =IF(F9<>"",HYPERLINK(F9,"→"),"") -> → | F9: =IFERROR(VLOOKUP(A9,红宝书去重版!$A:$S,11,FALSE),"") -> F:\《自创文法查阅Excel》4.1备份\《B词汇·红宝书》\红宝书15版图片\2172-きつえん【喫煙】.jpg | G9: =IF(H9<>"",HYPERLINK(H9,"▶"),"") -> ▶ | H9: =IFERROR(VLOOKUP(A9,红宝书去重版!$A:$S,18,FALSE),"") -> F:\《自创文法查阅Excel》4.1备份\《B词汇·红宝书》\红宝书MP3分割\07 n4-き (17).mp3
A10: 2234 | B10: きつえんせき | C10: 喫煙席 | D10: =IF(A10<>"",A10&" "&"[["&B10&" "&C10&"]]","") -> 2234 [[きつえんせき 喫煙席]] | E10: =IF(F10<>"",HYPERLINK(F10,"→"),"") -> → | F10: =IFERROR(VLOOKUP(A10,红宝书去重版!$A:$S,11,FALSE),"") -> F:\《自创文法查阅Excel》4.1备份\《B词汇·红宝书》\红宝书15版图片\2234-きつえんせき【喫煙席】.jpg | G10: =IF(H10<>"",HYPERLINK(H10,"▶"),"") -> ▶ | H10: =IFERROR(VLOOKUP(A10,红宝书去重版!$A:$S,18,FALSE),"") -> F:\《自创文法查阅Excel》4.1备份\《B词汇·红宝书》\红宝书MP3分割\07 n3-き (31).mp3
A11: 2288 | B11: きんえん | C11: 禁煙 | D11: =IF(A11<>"",A11&" "&"[["&B11&" "&C11&"]]","") -> 2288 [[きんえん 禁煙]] | E11: =IF(F11<>"",HYPERLINK(F11,"→"),"") -> → | F11: =IFERROR(VLOOKUP(A11,红宝书去重版!$A:$S,11,FALSE),"") -> F:\《自创文法查阅Excel》4.1备份\《B词汇·红宝书》\红宝书15版图片\2288-きんえん【禁煙】.jpg | G11: =IF(H11<>"",HYPERLINK(H11,"▶"),"") -> ▶ | H11: =IFERROR(VLOOKUP(A11,红宝书去重版!$A:$S,18,FALSE),"") -> F:\《自创文法查阅Excel》4.1备份\《B词汇·红宝书》\红宝书MP3分割\07 n3-き (85).mp3
A12: 2289 | B12: きんえんせき | C12: 禁煙席 | D12: =IF(A12<>"",A12&" "&"[["&B12&" "&C12&"]]","") -> 2289 [[きんえんせき 禁煙席]] | E12: =IF(F12<>"",HYPERLINK(F12,"→"),"") -> → | F12: =IFERROR(VLOOKUP(A12,红宝书去重版!$A:$S,11,FALSE),"") -> F:\《自创文法查阅Excel》4.1备份\《B词汇·红宝书》\红宝书15版图片\2289-きんえんせき【禁煙席】.jpg | G12: =IF(H12<>"",HYPERLINK(H12,"▶"),"") -> ▶ | H12: =IFERROR(VLOOKUP(A12,红宝书去重版!$A:$S,18,FALSE),"") -> F:\《自创文法查阅Excel》4.1备份\《B词汇·红宝书》\红宝书MP3分割\07 n3-き (86).mp3
D13: =IF(A13<>"",A13&" "&"[["&B13&" "&C13&"]]","") | E13: =IF(F13<>"",HYPERLINK(F13,"→"),"") | F13: =IFERROR(VLOOKUP(A13,红宝书去重版!$A:$S,11,FALSE),"") | G13: =IF(H13<>"",HYPERLINK(H13,"▶"),"") | H13: =IFERROR(VLOOKUP(A13,红宝书去重版!$A:$S,18,FALSE),"")
A14: 2829 | B14: けむい | C14: 煙い | D14: =IF(A14<>"",A14&" "&"[["&B14&" "&C14&"]]","") -> 2829 [[けむい 煙い]] | E14: =IF(F14<>"",HYPERLINK(F14,"→"),"") -> → | F14: =IFERROR(VLOOKUP(A14,红宝书去重版!$A:$S,11,FALSE),"") -> F:\《自创文法查阅Excel》4.1备份\《B词汇·红宝书》\红宝书15版图片\2829-けむい【煙い】.jpg | G14: =IF(H14<>"",HYPERLINK(H14,"▶"),"") -> ▶ | H14: =IFERROR(VLOOKUP(A14,红宝书去重版!$A:$S,18,FALSE),"") -> F:\《自创文法查阅Excel》4.1备份\《B词汇·红宝书》\红宝书MP3分割\09 n3-け (30).mp3
A15: 2830 | B15: けむり | C15: 煙 | D15: =IF(A15<>"",A15&" "&"[["&B15&" "&C15&"]]","") -> 2830 [[けむり 煙]] | E15: =IF(F15<>"",HYPERLINK(F15,"→"),"") -> → | F15: =IFERROR(VLOOKUP(A15,红宝书去重版!$A:$S,11,FALSE),"") -> F:\《自创文法查阅Excel》4.1备份\《B词汇·红宝书》\红宝书15版图片\2830-けむり【煙】.jpg | G15: =IF(H15<>"",HYPERLINK(H15,"▶"),"") -> ▶ | H15: =IFERROR(VLOOKUP(A15,红宝书去重版!$A:$S,18,FALSE),"") -> F:\《自创文法查阅Excel》4.1备份\《B词汇·红宝书》\红宝书MP3分割\09 n3-け (31).mp3
A16: 2894 | B16: けむる | C16: 煙る | D16: =IF(A16<>"",A16&" "&"[["&B16&" "&C16&"]]","") -> 2894 [[けむる 煙る]] | E16: =IF(F16<>"",HYPERLINK(F16,"→"),"") -> → | F16: =IFERROR(VLOOKUP(A16,红宝书去重版!$A:$S,11,FALSE),"") -> F:\《自创文法查阅Excel》4.1备份\《B词汇·红宝书》\红宝书15版图片\2894-けむる【煙る】.jpg | G16: =IF(H16<>"",HYPERLINK(H16,"▶"),"") -> ▶ | H16: =IFERROR(VLOOKUP(A16,红宝书去重版!$A:$S,18,FALSE),"") -> F:\《自创文法查阅Excel》4.1备份\《B词汇·红宝书》\红宝书MP3分割\09 n2-け (43).mp3
A17: 2966 | B17: けむたい | C17: 煙たい | D17: =IF(A17<>"",A17&" "&"[["&B17&" "&C17&"]]","") -> 2966 [[けむたい 煙たい]] | E17: =IF(F17<>"",HYPERLINK(F17,"→"),"") -> → | F17: =IFERROR(VLOOKUP(A17,红宝书去重版!$A:$S,11,FALSE),"") -> F:\《自创文法查阅Excel》4.1备份\《B词汇·红宝书》\红宝书15版图片\2966-けむたい【煙たい】.jpg | G17: =IF(H17<>"",HYPERLINK(H17,"▶"),"") -> ▶ | H17: =IFERROR(VLOOKUP(A17,红宝书去重版!$A:$S,18,FALSE),"") -> F:\《自创文法查阅Excel》4.1备份\《B词汇·红宝书》\红宝书MP3分割\09 n1-け (47).mp3
D18: =IF(A18<>"",A18&" "&"[["&B18&" "&C18&"]]","") | E18: =IF(F18<>"",HYPERLINK(F18,"→"),"") | F18: =IFERROR(VLOOKUP(A18,红宝书去重版!$A:$S,11,FALSE),"") | G18: =IF(H18<>"",HYPERLINK(H18,"▶"),"") | H18: =IFERROR(VLOOKUP(A18,红宝书去重版!$A:$S,18,FALSE),"")
A19: 5552 | B19: タバコ | C19: 煙草 | D19: =IF(A19<>"",A19&" "&"[["&B19&" "&C19&"]]","") -> 5552 [[タバコ 煙草]] | E19: =IF(F19<>"",HYPERLINK(F19,"→"),"") -> → | F19: =IFERROR(VLOOKUP(A19,红宝书去重版!$A:$S,11,FALSE),"") -> F:\《自创文法查阅Excel》4.1备份\《B词汇·红宝书》\红宝书15版图片\5552-タバコ【煙草】.jpg | G19: =IF(H19<>"",HYPERLINK(H19,"▶"),"") -> ▶ | H19: =IFERROR(VLOOKUP(A19,红宝书去重版!$A:$S,18,FALSE),"") -> F:\《自创文法查阅Excel》4.1备份\《B词汇·红宝书》\红宝书MP3分割\16 n5-た (31).mp3
D20: =IF(A20<>"",A20&" "&"[["&B20&" "&C20&"]]","") | E20: =IF(F20<>"",HYPERLINK(F20,"→"),"") | F20: =IFERROR(VLOOKUP(A20,红宝书去重版!$A:$S,11,FALSE),"") | G20: =IF(H20<>"",HYPERLINK(H20,"▶"),"") | H20: =IFERROR(VLOOKUP(A20,红宝书去重版!$A:$S,18,FALSE),"")
A21: 379 | B21: あんせい | C21: 安静 | D21: =IF(A21<>"",A21&" "&"[["&B21&" "&C21&"]]","") -> 379 [[あんせい 安静]] | E21: =IF(F21<>"",HYPERLINK(F21,"→"),"") -> → | F21: =IFERROR(VLOOKUP(A21,红宝书去重版!$A:$S,11,FALSE),"") -> F:\《自创文法查阅Excel》4.1备份\《B词汇·红宝书》\红宝书15版图片\379-あんせい【安静】.jpg | G21: =IF(H21<>"",HYPERLINK(H21,"▶"),"") -> ▶ | H21: =IFERROR(VLOOKUP(A21,红宝书去重版!$A:$S,18,FALSE),"") -> F:\《自创文法查阅Excel》4.1备份\《B词汇·红宝书》\红宝书MP3分割\01 n1-あ (130).mp3
A22: 2088 | B22: かんせい | C22: 閑静 | D22: =IF(A22<>"",A22&" "&"[["&B22&" "&C22&"]]","") -> 2088 [[かんせい 閑静]] | E22: =IF(F22<>"",HYPERLINK(F22,"→"),"") -> → | F22: =IFERROR(VLOOKUP(A22,红宝书去重版!$A:$S,11,FALSE),"") -> F:\《自创文法查阅Excel》4.1备份\《B词汇·红宝书》\红宝书15版图片\2088-かんせい【閑静】.jpg | G22: =IF(H22<>"",HYPERLINK(H22,"▶"),"") -> ▶ | H22: =IFERROR(VLOOKUP(A22,红宝书去重版!$A:$S,18,FALSE),"") -> F:\《自创文法查阅Excel》4.1备份\《B词汇·红宝书》\红宝书MP3分割\06 n1-か (187).mp3
A23: 5217 | B23: せいし | C23: 静止 | D23: =IF(A23<>"",A23&" "&"[["&B23&" "&C23&"]]","") -> 5217 [[せいし 静止]] | E23: =IF(F23<>"",HYPERLINK(F23,"→"),"") -> → | F23: =IFERROR(VLOOKUP(A23,红宝书去重版!$A:$S,11,FALSE),"") -> F:\《自创文法查阅Excel》4.1备份\《B词汇·红宝书》\红宝书15版图片\5217-せいし【静止】.jpg | G23: =IF(H23<>"",HYPERLINK(H23,"▶"),"") -> ▶ | H23: =IFERROR(VLOOKUP(A23,红宝书去重版!$A:$S,18,FALSE),"") -> F:\《自创文法查阅Excel》4.1备份\《B词汇·红宝书》\红宝书MP3分割\14 n1-せ (14).mp3
A24: 5228 | B24: せいてき | C24: 静的 | D24: =IF(A24<>"",A24&" "&"[["&B24&" "&C24&"]]","") -> 5228 [[せいてき 静的]] | E24: =IF(F24<>"",HYPERLINK(F24,"→"),"") -> → | F24: =IFERROR(VLOOKUP(A24,红宝书去重版!$A:$S,11,FALSE),"") -> F:\《自创文法查阅Excel》4.1备份\《B词汇·红宝书》\红宝书15版图片\5228-せいてき【静的】.jpg | G24: =IF(H24<>"",HYPERLINK(H24,"▶"),"") -> ▶ | H24: =IFERROR(VLOOKUP(A24,红宝书去重版!$A:$S,18,FALSE),"") -> F:\《自创文法查阅Excel》4.1备份\《B词汇·红宝书》\红宝书MP3分割\14 n1-せ (25).mp3
A25: 8461 | B25: へいせい | C25: 平静 | D25: =IF(A25<>"",A25&" "&"[["&B25&" "&C25&"]]","") -> 8461 [[へいせい 平静]] | E25: =IF(F25<>"",HYPERLINK(F25,"→"),"") -> → | F25: =IFERROR(VLOOKUP(A25,红宝书去重版!$A:$S,11,FALSE),"") -> F:\《自创文法查阅Excel》4.1备份\《B词汇·红宝书》\红宝书15版图片\8461-へいせい【平静】.jpg | G25: =IF(H25<>"",HYPERLINK(H25,"▶"),"") -> ▶ | H25: =IFERROR(VLOOKUP(A25,红宝书去重版!$A:$S,18,FALSE),"") -> F:\《自创文法查阅Excel》4.1备份\《B词汇·红宝书》\红宝书MP3分割\29 n1-へ (7).mp3
A26: 9918 | B26: れいせい | C26: 冷静 | D26: =IF(A26<>"",A26&" "&"[["&B26&" "&C26&"]]","") -> 9918 [[れいせい 冷静]] | E26: =IF(F26<>"",HYPERLINK(F26,"→"),"") -> → | F26: =IFERROR(VLOOKUP(A26,红宝书去重版!$A:$S,11,FALSE),"") -> F:\《自创文法查阅Excel》4.1备份\《B词汇·红宝书》\红宝书15版图片\9918-れいせい【冷静】.jpg | G26: =IF(H26<>"",HYPERLINK(H26,"▶"),"") -> ▶ | H26: =IFERROR(VLOOKUP(A26,红宝书去重版!$A:$S,18,FALSE),"") -> F:\《自创文法查阅Excel》4.1备份\《B词汇·红宝书》\红宝书MP3分割\44 n2-れ (1).mp3
D27: =IF(A27<>"",A27&" "&"[["&B27&" "&C27&"]]","") | E27: =IF(F27<>"",HYPERLINK(F27,"→"),"") | F27: =IFERROR(VLOOKUP(A27,红宝书去重版!$A:$S,11,FALSE),"") | G27: =IF(H27<>"",HYPERLINK(H27,"▶"),"") | H27: =IFERROR(VLOOKUP(A27,红宝书去重版!$A:$S,18,FALSE),"")
A28: 2161 | B28: きけん | C28: 危険 | D28: =IF(A28<>"",A28&" "&"[["&B28&" "&C28&"]]","") -> 2161 [[きけん 危険]] | E28: =IF(F28<>"",HYPERLINK(F28,"→"),"") -> → | F28: =IFERROR(VLOOKUP(A28,红宝书去重版!$A:$S,11,FALSE),"") -> F:\《自创文法查阅Excel》4.1备份\《B词汇·红宝书》\红宝书15版图片\2161-きけん【危険】.jpg | G28: =IF(H28<>"",HYPERLINK(H28,"▶"),"") -> ▶ | H28: =IFERROR(VLOOKUP(A28,红宝书去重版!$A:$S,18,FALSE),"") -> F:\《自创文法查阅Excel》4.1备份\《B词汇·红宝书》\红宝书MP3分割\07 n4-き (6).mp3
A29: 2309 | B29: きき | C29: 危機 | D29: =IF(A29<>"",A29&" "&"[["&B29&" "&C29&"]]","") -> 2309 [[きき 危機]] | E29: =IF(F29<>"",HYPERLINK(F29,"→"),"") -> → | F29: =IFERROR(VLOOKUP(A29,红宝书去重版!$A:$S,11,FALSE),"") -> F:\《自创文法查阅Excel》4.1备份\《B词汇·红宝书》\红宝书15版图片\2309-きき【危機】.jpg | G29: =IF(H29<>"",HYPERLINK(H29,"▶"),"") -> ▶ | H29: =IFERROR(VLOOKUP(A29,红宝书去重版!$A:$S,18,FALSE),"") -> F:\《自创文法查阅Excel》4.1备份\《B词汇·红宝书》\红宝书MP3分割\07 n2-き (11).mp3
A30: 2393 | B30: きがい | C30: 危害 | D30: =IF(A30<>"",A30&" "&"[["&B30&" "&C30&"]]","") -> 2393 [[きがい 危害]] | E30: =IF(F30<>"",HYPERLINK(F30,"→"),"") -> → | F30: =IFERROR(VLOOKUP(A30,红宝书去重版!$A:$S,11,FALSE),"") -> F:\《自创文法查阅Excel》4.1备份\《B词汇·红宝书》\红宝书15版图片\2393-きがい【危害】.jpg | G30: =IF(H30<>"",HYPERLINK(H30,"▶"),"") -> ▶ | H30: =IFERROR(VLOOKUP(A30,红宝书去重版!$A:$S,18,FALSE),"") -> F:\《自创文法查阅Excel》4.1备份\《B词汇·红宝书》\红宝书MP3分割\07 n1-き (4).mp3
D31: =IF(A31<>"",A31&" "&"[["&B31&" "&C31&"]]","") | E31: =IF(F31<>"",HYPERLINK(F31,"→"),"") | F31: =IFERROR(VLOOKUP(A31,红宝书去重版!$A:$S,11,FALSE),"") | G31: =IF(H31<>"",HYPERLINK(H31,"▶"),"") | H31: =IFERROR(VLOOKUP(A31,红宝书去重版!$A:$S,18,FALSE),"")
A32: 39 | B32: あぶない | C32: 危ない | D32: =IF(A32<>"",A32&" "&"[["&B32&" "&C32&"]]","") -> 39 [[あぶない 危ない]] | E32: =IF(F32<>"",HYPERLINK(F32,"→"),"") -> → | F32: =IFERROR(VLOOKUP(A32,红宝书去重版!$A:$S,11,FALSE),"") -> F:\《自创文法查阅Excel》4.1备份\《B词汇·红宝书》\红宝书15版图片\39-あぶない【危ない】.jpg | G32: =IF(H32<>"",HYPERLINK(H32,"▶"),"") -> ▶ | H32: =IFERROR(VLOOKUP(A32,红宝书去重版!$A:$S,18,FALSE),"") -> F:\《自创文法查阅Excel》4.1备份\《B词汇·红宝书》\红宝书MP3分割\01 n5-あ (39).mp3
A33: 338 | B33: あぶなげない | C33: 危な気ない | D33: =IF(A33<>"",A33&" "&"[["&B33&" "&C33&"]]","") -> 338 [[あぶなげない 危な気ない]] | E33: =IF(F33<>"",HYPERLINK(F33,"→"),"") -> → | F33: =IFERROR(VLOOKUP(A33,红宝书去重版!$A:$S,11,FALSE),"") -> F:\《自创文法查阅Excel》4.1备份\《B词汇·红宝书》\红宝书15版图片\338-あぶなげない【危な気ない】.jpg | G33: =IF(H33<>"",HYPERLINK(H33,"▶"),"") -> ▶ | H33: =IFERROR(VLOOKUP(A33,红宝书去重版!$A:$S,18,FALSE),"") -> F:\《自创文法查阅Excel》4.1备份\《B词汇·红宝书》\红宝书MP3分割\01 n1-あ (89).mp3
D34: =IF(A34<>"",A34&" "&"[["&B34&" "&C34&"]]","") | E34: =IF(F34<>"",HYPERLINK(F34,"→"),"") | F34: =IFERROR(VLOOKUP(A34,红宝书去重版!$A:$S,11,FALSE),"") | G34: =IF(H34<>"",HYPERLINK(H34,"▶"),"") | H34: =IFERROR(VLOOKUP(A34,红宝书去重版!$A:$S,18,FALSE),"")
A35: 150 | B35: あやうく | C35: 危うく | D35: =IF(A35<>"",A35&" "&"[["&B35&" "&C35&"]]","") -> 150 [[あやうく 危うく]] | E35: =IF(F35<>"",HYPERLINK(F35,"→"),"") -> → | F35: =IFERROR(VLOOKUP(A35,红宝书去重版!$A:$S,11,FALSE),"") -> F:\《自创文法查阅Excel》4.1备份\《B词汇·红宝书》\红宝书15版图片\150-あやうく【危うく】.jpg | G35: =IF(H35<>"",HYPERLINK(H35,"▶"),"") -> ▶ | H35: =IFERROR(VLOOKUP(A35,红宝书去重版!$A:$S,18,FALSE),"") -> F:\《自创文法查阅Excel》4.1备份\《B词汇·红宝书》\红宝书MP3分割\01 n3-あ (41).mp3
A36: 225 | B36: あやうい | C36: 危うい | D36: =IF(A36<>"",A36&" "&"[["&B36&" "&C36&"]]","") -> 225 [[あやうい 危うい]] | E36: =IF(F36<>"",HYPERLINK(F36,"→"),"") -> → | F36: =IFERROR(VLOOKUP(A36,红宝书去重版!$A:$S,11,FALSE),"") -> F:\《自创文法查阅Excel》4.1备份\《B词汇·红宝书》\红宝书15版图片\225-あやうい【危うい】.jpg | G36: =IF(H36<>"",HYPERLINK(H36,"▶"),"") -> ▶ | H36: =IFERROR(VLOOKUP(A36,红宝书去重版!$A:$S,18,FALSE),"") -> F:\《自创文法查阅Excel》4.1备份\《B词汇·红宝书》\红宝书MP3分割\01 n2-あ (50).mp3
A37: 350 | B37: あやぶむ | C37: 危ぶむ | D37: =IF(A37<>"",A37&" "&"[["&B37&" "&C37&"]]","") -> 350 [[あやぶむ 危ぶむ]] | E37: =IF(F37<>"",HYPERLINK(F37,"→"),"") -> → | F37: =IFERROR(VLOOKUP(A37,红宝书去重版!$A:$S,11,FALSE),"") -> F:\《自创文法查阅Excel》4.1备份\《B词汇·红宝书》\红宝书15版图片\350-あやぶむ【危ぶむ】.jpg | G37: =IF(H37<>"",HYPERLINK(H37,"▶"),"") -> ▶ | H37: =IFERROR(VLOOKUP(A37,红宝书去重版!$A:$S,18,FALSE),"") -> F:\《自创文法查阅Excel》4.1备份\《B词汇·红宝书》\红宝书MP3分割\01 n1-あ (101).mp3
D38: =IF(A38<>"",A38&" "&"[["&B38&" "&C38&"]]","") | E38: =IF(F38<>"",HYPERLINK(F38,"→"),"") | F38: =IFERROR(VLOOKUP(A38,红宝书去重版!$A:$S,11,FALSE),"") | G38: =IF(H38<>"",HYPERLINK(H38,"▶"),"") | H38: =IFERROR(VLOOKUP(A38,红宝书去重版!$A:$S,18,FALSE),"")
A39: 2161 | B39: きけん | C39: 危険 | D39: =IF(A39<>"",A39&" "&"[["&B39&" "&C39&"]]","") -> 2161 [[きけん 危険]] | E39: =IF(F39<>"",HYPERLINK(F39,"→"),"") -> → | F39: =IFERROR(VLOOKUP(A39,红宝书去重版!$A:$S,11,FALSE),"") -> F:\《自创文法查阅Excel》4.1备份\《B词汇·红宝书》\红宝书15版图片\2161-きけん【危険】.jpg | G39: =IF(H39<>"",HYPERLINK(H39,"▶"),"") -> ▶ | H39: =IFERROR(VLOOKUP(A39,红宝书去重版!$A:$S,18,FALSE),"") -> F:\《自创文法查阅Excel》4.1备份\《B词汇·红宝书》\红宝书MP3分割\07 n4-き (6).mp3
A40: 5917 | B40: たんけん | C40: 探検/探険 | D40: =IF(A40<>"",A40&" "&"[["&B40&" "&C40&"]]","") -> 5917 [[たんけん 探検/探険]] | E40: =IF(F40<>"",HYPERLINK(F40,"→"),"") -> → | F40: =IFERROR(VLOOKUP(A40,红宝书去重版!$A:$S,11,FALSE),"") -> F:\《自创文法查阅Excel》4.1备份\《B词汇·红宝书》\红宝书15版图片\5917-たんけん【探検·探険】.jpg | G40: =IF(H40<>"",HYPERLINK(H40,"▶"),"") -> ▶ | H40: =IFERROR(VLOOKUP(A40,红宝书去重版!$A:$S,18,FALSE),"") -> F:\《自创文法查阅Excel》4.1备份\《B词汇·红宝书》\红宝书MP3分割\16 n1-た (108).mp3
A41: 8569 | B41: ぼうけん | C41: 冒険 | D41: =IF(A41<>"",A41&" "&"[["&B41&" "&C41&"]]","") -> 8569 [[ぼうけん 冒険]] | E41: =IF(F41<>"",HYPERLINK(F41,"→"),"") -> → | F41: =IFERROR(VLOOKUP(A41,红宝书去重版!$A:$S,11,FALSE),"") -> F:\《自创文法查阅Excel》4.1备份\《B词汇·红宝书》\红宝书15版图片\8569-ぼうけん【冒険】.jpg | G41: =IF(H41<>"",HYPERLINK(H41,"▶"),"") -> ▶ | H41: =IFERROR(VLOOKUP(A41,红宝书去重版!$A:$S,18,FALSE),"") -> F:\《自创文法查阅Excel》4.1备份\《B词汇·红宝书》\红宝书MP3分割\30 n2-ほ (6).mp3
A42: 8595 | B42: ほけん | C42: 保険 | D42: =IF(A42<>"",A42&" "&"[["&B42&" "&C42&"]]","") -> 8595 [[ほけん 保険]] | E42: =IF(F42<>"",HYPERLINK(F42,"→"),"") -> → | F42: =IFERROR(VLOOKUP(A42,红宝书去重版!$A:$S,11,FALSE),"") -> F:\《自创文法查阅Excel》4.1备份\《B词汇·红宝书》\红宝书15版图片\8595-ほけん【保険】.jpg | G42: =IF(H42<>"",HYPERLINK(H42,"▶"),"") -> ▶ | H42: =IFERROR(VLOOKUP(A42,红宝书去重版!$A:$S,18,FALSE),"") -> F:\《自创文法查阅Excel》4.1备份\《B词汇·红宝书》\红宝书MP3分割\30 n2-ほ (32).mp3
D43: =IF(A43<>"",A43&" "&"[["&B43&" "&C43&"]]","") | E43: =IF(F43<>"",HYPERLINK(F43,"→"),"") | F43: =IFERROR(VLOOKUP(A43,红宝书去重版!$A:$S,11,FALSE),"") | G43: =IF(H43<>"",HYPERLINK(H43,"▶"),"") | H43: =IFERROR(VLOOKUP(A43,红宝书去重版!$A:$S,18,FALSE),"")
A44: 2895 | B44: けわしい | C44: 険しい | D44: =IF(A44<>"",A44&" "&"[["&B44&" "&C44&"]]","") -> 2895 [[けわしい 険しい]] | E44: =IF(F44<>"",HYPERLINK(F44,"→"),"") -> → | F44: =IFERROR(VLOOKUP(A44,红宝书去重版!$A:$S,11,FALSE),"") -> F:\《自创文法查阅Excel》4.1备份\《B词汇·红宝书》\红宝书15版图片\2895-けわしい【険しい】.jpg | G44: =IF(H44<>"",HYPERLINK(H44,"▶"),"") -> ▶ | H44: =IFERROR(VLOOKUP(A44,红宝书去重版!$A:$S,18,FALSE),"") -> F:\《自创文法查阅Excel》4.1备份\《B词汇·红宝书》\红宝书MP3分割\09 n2-け (44).mp3
D45: =IF(A45<>"",A45&" "&"[["&B45&" "&C45&"]]","") | E45: =IF(F45<>"",HYPERLINK(F45,"→"),"") | F45: =IFERROR(VLOOKUP(A45,红宝书去重版!$A:$S,11,FALSE),"") | G45: =IF(H45<>"",HYPERLINK(H45,"▶"),"") | H45: =IFERROR(VLOOKUP(A45,红宝书去重版!$A:$S,18,FALSE),"")
A46: 1560 | B46: かんけい | C46: 関係 | D46: =IF(A46<>"",A46&" "&"[["&B46&" "&C46&"]]","") -> 1560 [[かんけい 関係]] | E46: =IF(F46<>"",HYPERLINK(F46,"→"),"") -> → | F46: =IFERROR(VLOOKUP(A46,红宝书去重版!$A:$S,11,FALSE),"") -> F:\《自创文法查阅Excel》4.1备份\《B词汇·红宝书》\红宝书15版图片\1560-かんけい【関係】.jpg | G46: =IF(H46<>"",HYPERLINK(H46,"▶"),"") -> ▶ | H46: =IFERROR(VLOOKUP(A46,红宝书去重版!$A:$S,18,FALSE),"") -> F:\《自创文法查阅Excel》4.1备份\《B词汇·红宝书》\红宝书MP3分割\06 n4-か (80).mp3
A47: 1712 | B47: かんさい | C47: 関西 | D47: =IF(A47<>"",A47&" "&"[["&B47&" "&C47&"]]","") -> 1712 [[かんさい 関西]] | E47: =IF(F47<>"",HYPERLINK(F47,"→"),"") -> → | F47: =IFERROR(VLOOKUP(A47,红宝书去重版!$A:$S,11,FALSE),"") -> F:\《自创文法查阅Excel》4.1备份\《B词汇·红宝书》\红宝书15版图片\1712-かんさい【関西】.jpg | G47: =IF(H47<>"",HYPERLINK(H47,"▶"),"") -> ▶ | H47: =IFERROR(VLOOKUP(A47,红宝书去重版!$A:$S,18,FALSE),"") -> F:\《自创文法查阅Excel》4.1备份\《B词汇·红宝书》\红宝书MP3分割\06 n3-か (141).mp3
A48: 1721 | B48: かんしん | C48: 関心 | D48: =IF(A48<>"",A48&" "&"[["&B48&" "&C48&"]]","") -> 1721 [[かんしん 関心]] | E48: =IF(F48<>"",HYPERLINK(F48,"→"),"") -> → | F48: =IFERROR(VLOOKUP(A48,红宝书去重版!$A:$S,11,FALSE),"") -> F:\《自创文法查阅Excel》4.1备份\《B词汇·红宝书》\红宝书15版图片\1721-かんしん【関心】.jpg | G48: =IF(H48<>"",HYPERLINK(H48,"▶"),"") -> ▶ | H48: =IFERROR(VLOOKUP(A48,红宝书去重版!$A:$S,18,FALSE),"") -> F:\《自创文法查阅Excel》4.1备份\《B词汇·红宝书》\红宝书MP3分割\06 n3-か (150).mp3
A49: 1722 | B49: かんする | C49: 関する | D49: =IF(A49<>"",A49&" "&"[["&B49&" "&C49&"]]","") -> 1722 [[かんする 関する]] | E49: =IF(F49<>"",HYPERLINK(F49,"→"),"") -> → | F49: =IFERROR(VLOOKUP(A49,红宝书去重版!$A:$S,11,FALSE),"") -> F:\《自创文法查阅Excel》4.1备份\《B词汇·红宝书》\红宝书15版图片\1722-かんする【関する】.jpg | G49: =IF(H49<>"",HYPERLINK(H49,"▶"),"") -> ▶ | H49: =IFERROR(VLOOKUP(A49,红宝书去重版!$A:$S,18,FALSE),"") -> F:\《自创文法查阅Excel》4.1备份\《B词汇·红宝书》\红宝书MP3分割\06 n3-か (151).mp3
A50: 1729 | B50: かんとう | C50: 関東 | D50: =IF(A50<>"",A50&" "&"[["&B50&" "&C50&"]]","") -> 1729 [[かんとう 関東]] | E50: =IF(F50<>"",HYPERLINK(F50,"→"),"") -> → | F50: =IFERROR(VLOOKUP(A50,红宝书去重版!$A:$S,11,FALSE),"") -> F:\《自创文法查阅Excel》4.1备份\《B词汇·红宝书》\红宝书15版图片\1729-かんとう【関東】.jpg | G50: =IF(H50<>"",HYPERLINK(H50,"▶"),"") -> ▶ | H50: =IFERROR(VLOOKUP(A50,红宝书去重版!$A:$S,18,FALSE),"") -> F:\《自创文法查阅Excel》4.1备份\《B词汇·红宝书》\红宝书MP3分割\06 n3-か (158).mp3
A51: 1901 | B51: かんれん | C51: 関連 | D51: =IF(A51<>"",A51&" "&"[["&B51&" "&C51&"]]","") -> 1901 [[かんれん 関連]] | E51: =IF(F51<>"",HYPERLINK(F51,"→"),"") -> → | F51: =IFERROR(VLOOKUP(A51,红宝书去重版!$A:$S,11,FALSE),"") -> F:\《自创文法查阅Excel》4.1备份\《B词汇·红宝书》\红宝书15版图片\1901-かんれん【関連】.jpg | G51: =IF(H51<>"",HYPERLINK(H51,"▶"),"") -> ▶ | H51: =IFERROR(VLOOKUP(A51,红宝书去重版!$A:$S,18,FALSE),"") -> F:\《自创文法查阅Excel》4.1备份\《B词汇·红宝书》\红宝书MP3分割\06 n2-か (165).mp3
A52: 2090 | B52: かんぜい | C52: 関税 | D52: =IF(A52<>"",A52&" "&"[["&B52&" "&C52&"]]","") -> 2090 [[かんぜい 関税]] | E52: =IF(F52<>"",HYPERLINK(F52,"→"),"") -> → | F52: =IFERROR(VLOOKUP(A52,红宝书去重版!$A:$S,11,FALSE),"") -> F:\《自创文法查阅Excel》4.1备份\《B词汇·红宝书》\红宝书15版图片\2090-かんぜい【関税】.jpg | G52: =IF(H52<>"",HYPERLINK(H52,"▶"),"") -> ▶ | H52: =IFERROR(VLOOKUP(A52,红宝书去重版!$A:$S,18,FALSE),"") -> F:\《自创文法查阅Excel》4.1备份\《B词汇·红宝书》\红宝书MP3分割\06 n1-か (189).mp3
A53: 2092 | B53: かんせつ | C53: 関節 | D53: =IF(A53<>"",A53&" "&"[["&B53&" "&C53&"]]","") -> 2092 [[かんせつ 関節]] | E53: =IF(F53<>"",HYPERLINK(F53,"→"),"") -> → | F53: =IFERROR(VLOOKUP(A53,红宝书去重版!$A:$S,11,FALSE),"") -> F:\《自创文法查阅Excel》4.1备份\《B词汇·红宝书》\红宝书15版图片\2092-かんせつ【関節】.jpg | G53: =IF(H53<>"",HYPERLINK(H53,"▶"),"") -> ▶ | H53: =IFERROR(VLOOKUP(A53,红宝书去重版!$A:$S,18,FALSE),"") -> F:\《自创文法查阅Excel》4.1备份\《B词汇·红宝书》\红宝书MP3分割\06 n1-か (191).mp3
A54: 2096 | B54: かんち | C54: 関知 | D54: =IF(A54<>"",A54&" "&"[["&B54&" "&C54&"]]","") -> 2096 [[かんち 関知]] | E54: =IF(F54<>"",HYPERLINK(F54,"→"),"") -> → | F54: =IFERROR(VLOOKUP(A54,红宝书去重版!$A:$S,11,FALSE),"") -> F:\《自创文法查阅Excel》4.1备份\《B词汇·红宝书》\红宝书15版图片\2096-かんち【関知】.jpg | G54: =IF(H54<>"",HYPERLINK(H54,"▶"),"") -> ▶ | H54: =IFERROR(VLOOKUP(A54,红宝书去重版!$A:$S,18,FALSE),"") -> F:\《自创文法查阅Excel》4.1备份\《B词汇·红宝书》\红宝书MP3分割\06 n1-か (195).mp3
A55: 2111 | B55: かんよ | C55: 関与 | D55: =IF(A55<>"",A55&" "&"[["&B55&" "&C55&"]]","") -> 2111 [[かんよ 関与]] | E55: =IF(F55<>"",HYPERLINK(F55,"→"),"") -> → | F55: =IFERROR(VLOOKUP(A55,红宝书去重版!$A:$S,11,FALSE),"") -> F:\《自创文法查阅Excel》4.1备份\《B词汇·红宝书》\红宝书15版图片\2111-かんよ【関与】.jpg | G55: =IF(H55<>"",HYPERLINK(H55,"▶"),"") -> ▶ | H55: =IFERROR(VLOOKUP(A55,红宝书去重版!$A:$S,18,FALSE),"") -> F:\《自创文法查阅Excel》4.1备份\《B词汇·红宝书》\红宝书MP3分割\06 n1-か (210).mp3
A56: 2307 | B56: きかん | C56: 機関 | D56: =IF(A56<>"",A56&" "&"[["&B56&" "&C56&"]]","") -> 2307 [[きかん 機関]] | E56: =IF(F56<>"",HYPERLINK(F56,"→"),"") -> → | F56: =IFERROR(VLOOKUP(A56,红宝书去重版!$A:$S,11,FALSE),"") -> F:\《自创文法查阅Excel》4.1备份\《B词汇·红宝书》\红宝书15版图片\2307-きかん【機関】.jpg | G56: =IF(H56<>"",HYPERLINK(H56,"▶"),"") -> ▶ | H56: =IFERROR(VLOOKUP(A56,红宝书去重版!$A:$S,18,FALSE),"") -> F:\《自创文法查阅Excel》4.1备份\《B词汇·红宝书》\红宝书MP3分割\07 n2-き (9).mp3
A57: 2308 | B57: きかんしゃ | C57: 機関車 | D57: =IF(A57<>"",A57&" "&"[["&B57&" "&C57&"]]","") -> 2308 [[きかんしゃ 機関車]] | E57: =IF(F57<>"",HYPERLINK(F57,"→"),"") -> → | F57: =IFERROR(VLOOKUP(A57,红宝书去重版!$A:$S,11,FALSE),"") -> F:\《自创文法查阅Excel》4.1备份\《B词汇·红宝书》\红宝书15版图片\2308-きかんしゃ【機関車】.jpg | G57: =IF(H57<>"",HYPERLINK(H57,"▶"),"") -> ▶ | H57: =IFERROR(VLOOKUP(A57,红宝书去重版!$A:$S,18,FALSE),"") -> F:\《自创文法查阅Excel》4.1备份\《B词汇·红宝书》\红宝书MP3分割\07 n2-き (10).mp3
... A61: 9075 | B61: むかんしん | C61: 無関心 | D61: =IF(A61<>"",A61&" "&"[["&B61&" "&C61&"]]","") -> 9075 [[むかんしん 無関心]] | E61: =IF(F61<>"",HYPERLINK(F61,"→"),"") -> → | F61: =IFERROR(VLOOKUP(A61,红宝书去重版!$A:$S,11,FALSE),"") -> F:\《自创文法查阅Excel》4.1备份\《B词汇·红宝书》\红宝书15版图片\9075-むかんしん【無関心】.jpg | G61: =IF(H61<>"",HYPERLINK(H61,"▶"),"") -> ▶ | H61: =IFERROR(VLOOKUP(A61,红宝书去重版!$A:$S,18,FALSE),"") -> F:\《自创文法查阅Excel》4.1备份\《B词汇·红宝书》\红宝书MP3分割\33 n3-む (3).mp3
D62: =IF(A62<>"",A62&" "&"[["&B62&" "&C62&"]]","") | E62: =IF(F62<>"",HYPERLINK(F62,"→"),"") | F62: =IFERROR(VLOOKUP(A62,红宝书去重版!$A:$S,11,FALSE),"") | G62: =IF(H62<>"",HYPERLINK(H62,"▶"),"") | H62: =IFERROR(VLOOKUP(A62,红宝书去重版!$A:$S,18,FALSE),"")
A63: 1609 | B63: かかわる | C63: 関わる | D63: =IF(A63<>"",A63&" "&"[["&B63&" "&C63&"]]","") -> 1609 [[かかわる 関わる]] | E63: =IF(F63<>"",HYPERLINK(F63,"→"),"") -> → | F63: =IFERROR(VLOOKUP(A63,红宝书去重版!$A:$S,11,FALSE),"") -> F:\《自创文法查阅Excel》4.1备份\《B词汇·红宝书》\红宝书15版图片\1609-かかわる【関わる】.jpg | G63: =IF(H63<>"",HYPERLINK(H63,"▶"),"") -> ▶ | H63: =IFERROR(VLOOKUP(A63,红宝书去重版!$A:$S,18,FALSE),"") -> F:\《自创文法查阅Excel》4.1备份\《B词汇·红宝书》\红宝书MP3分割\06 n3-か (38).mp3
D64: =IF(A64<>"",A64&" "&"[["&B64&" "&C64&"]]","") | E64: =IF(F64<>"",HYPERLINK(F64,"→"),"") | F64: =IFERROR(VLOOKUP(A64,红宝书去重版!$A:$S,11,FALSE),"") | G64: =IF(H64<>"",HYPERLINK(H64,"▶"),"") | H64: =IFERROR(VLOOKUP(A64,红宝书去重版!$A:$S,18,FALSE),"")
A65: 1560 | B65: かんけい | C65: 関係 | D65: =IF(A65<>"",A65&" "&"[["&B65&" "&C65&"]]","") -> 1560 [[かんけい 関係]] | E65: =IF(F65<>"",HYPERLINK(F65,"→"),"") -> → | F65: =IFERROR(VLOOKUP(A65,红宝书去重版!$A:$S,11,FALSE),"") -> F:\《自创文法查阅Excel》4.1备份\《B词汇·红宝书》\红宝书15版图片\1560-かんけい【関係】.jpg | G65: =IF(H65<>"",HYPERLINK(H65,"▶"),"") -> ▶ | H65: =IFERROR(VLOOKUP(A65,红宝书去重版!$A:$S,18,FALSE),"") -> F:\《自创文法查阅Excel》4.1备份\《B词汇·红宝书》\红宝书MP3分割\06 n4-か (80).mp3
D66: =IF(A66<>"",A66&" "&"[["&B66&" "&C66&"]]","") | E66: =IF(F66<>"",HYPERLINK(F66,"→"),"") | F66: =IFERROR(VLOOKUP(A66,红宝书去重版!$A:$S,11,FALSE),"") | G66: =IF(H66<>"",HYPERLINK(H66,"▶"),"") | H66: =IFERROR(VLOOKUP(A66,红宝书去重版!$A:$S,18,FALSE),"")
A67: 1499 | B67: かかり | C67: 係り | D67: =IF(A67<>"",A67&" "&"[["&B67&" "&C67&"]]","") -> 1499 [[かかり 係り]] | E67: =IF(F67<>"",HYPERLINK(F67,"→"),"") -> → | F67: =IFERROR(VLOOKUP(A67,红宝书去重版!$A:$S,11,FALSE),"") -> F:\《自创文法查阅Excel》4.1备份\《B词汇·红宝书》\红宝书15版图片\1499-かかり【係り】.jpg | G67: =IF(H67<>"",HYPERLINK(H67,"▶"),"") -> ▶ | H67: =IFERROR(VLOOKUP(A67,红宝书去重版!$A:$S,18,FALSE),"") -> F:\《自创文法查阅Excel》4.1备份\《B词汇·红宝书》\红宝书MP3分割\06 n4-か (19).mp3
A68: 1501 | B68: かかりいん | C68: 係員 | D68: =IF(A68<>"",A68&" "&"[["&B68&" "&C68&"]]","") -> 1501 [[かかりいん 係員]] | E68: =IF(F68<>"",HYPERLINK(F68,"→"),"") -> → | F68: =IFERROR(VLOOKUP(A68,红宝书去重版!$A:$S,11,FALSE),"") -> F:\《自创文法查阅Excel》4.1备份\《B词汇·红宝书》\红宝书15版图片\1501-かかりいん【係員】.jpg | G68: =IF(H68<>"",HYPERLINK(H68,"▶"),"") -> ▶ | H68: =IFERROR(VLOOKUP(A68,红宝书去重版!$A:$S,18,FALSE),"") -> F:\《自创文法查阅Excel》4.1备份\《B词汇·红宝书》\红宝书MP3分割\06 n4-か (21).mp3
D69: =IF(A69<>"",A69&" "&"[["&B69&" "&C69&"]]","") | E69: =IF(F69<>"",HYPERLINK(F69,"→"),"") | F69: =IFERROR(VLOOKUP(A69,红宝书去重版!$A:$S,11,FALSE),"") | G69: =IF(H69<>"",HYPERLINK(H69,"▶"),"") | H69: =IFERROR(VLOOKUP(A69,红宝书去重版!$A:$S,18,FALSE),"")
A70: 767 | B70: うけつけがかり | C70: 受付係 | D70: =IF(A70<>"",A70&" "&"[["&B70&" "&C70&"]]","") -> 767 [[うけつけがかり 受付係]] | E70: =IF(F70<>"",HYPERLINK(F70,"→"),"") -> → | F70: =IFERROR(VLOOKUP(A70,红宝书去重版!$A:$S,11,FALSE),"") -> F:\《自创文法查阅Excel》4.1备份\《B词汇·红宝书》\红宝书15版图片\767-うけつけがかり【受付係】.jpg | G70: =IF(H70<>"",HYPERLINK(H70,"▶"),"") -> ▶ | H70: =IFERROR(VLOOKUP(A70,红宝书去重版!$A:$S,18,FALSE),"") -> F:\《自创文法查阅Excel》4.1备份\《B词汇·红宝书》\红宝书MP3分割\03 n4-う (4).mp3
A71: 1500 | B71: ～がかり | C71: ～係 | D71: =IF(A71<>"",A71&" "&"[["&B71&" "&C71&"]]","") -> 1500 [[～がかり ～係]] | E71: =IF(F71<>"",HYPERLINK(F71,"→"),"") -> → | F71: =IFERROR(VLOOKUP(A71,红宝书去重版!$A:$S,11,FALSE),"") -> F:\《自创文法查阅Excel》4.1备份\《B词汇·红宝书》\红宝书15版图片\1500-～がかり【～係】.jpg | G71: =IF(H71<>"",HYPERLINK(H71,"▶"),"") -> ▶ | H71: =IFERROR(VLOOKUP(A71,红宝书去重版!$A:$S,18,FALSE),"") -> F:\《自创文法查阅Excel》4.1备份\《B词汇·红宝书》\红宝书MP3分割\06 n4-か (20).mp3
D72: =IF(A72<>"",A72&" "&"[["&B72&" "&C72&"]]","") | E72: =IF(F72<>"",HYPERLINK(F72,"→"),"") | F72: =IFERROR(VLOOKUP(A72,红宝书去重版!$A:$S,11,FALSE),"") | G72: =IF(H72<>"",HYPERLINK(H72,"▶"),"") | H72: =IFERROR(VLOOKUP(A72,红宝书去重版!$A:$S,18,FALSE),"")
A73: 2116 | B73: かんらく | C73: 陥落 | D73: =IF(A73<>"",A73&" "&"[["&B73&" "&C73&"]]","") -> 2116 [[かんらく 陥落]] | E73: =IF(F73<>"",HYPERLINK(F73,"→"),"") -> → | F73: =IFERROR(VLOOKUP(A73,红宝书去重版!$A:$S,11,FALSE),"") -> F:\《自创文法查阅Excel》4.1备份\《B词汇·红宝书》\红宝书15版图片\2116-かんらく【陥落】.jpg | G73: =IF(H73<>"",HYPERLINK(H73,"▶"),"") -> ▶ | H73: =IFERROR(VLOOKUP(A73,红宝书去重版!$A:$S,18,FALSE),"") -> F:\《自创文法查阅Excel》4.1备份\《B词汇·红宝书》\红宝书MP3分割\06 n1-か (215).mp3
A74: 2483 | B74: きゅうらく | C74: 急落 | D74: =IF(A74<>"",A74&" "&"[["&B74&" "&C74&"]]","") -> 2483 [[きゅうらく 急落]] | E74: =IF(F74<>"",HYPERLINK(F74,"→"),"") -> → | F74: =IFERROR(VLOOKUP(A74,红宝书去重版!$A:$S,11,FALSE),"") -> F:\《自创文法查阅Excel》4.1备份\《B词汇·红宝书》\红宝书15版图片\2483-きゅうらく【急落】.jpg | G74: =IF(H74<>"",HYPERLINK(H74,"▶"),"") -> ▶ | H74: =IFERROR(VLOOKUP(A74,红宝书去重版!$A:$S,18,FALSE),"") -> F:\《自创文法查阅Excel》4.1备份\《B词汇·红宝书》\红宝书MP3分割\07 n1-き (94).mp3
A75: 2970 | B75: げらく | C75: 下落 | D75: =IF(A75<>"",A75&" "&"[["&B75&" "&C75&"]]","") -> 2970 [[げらく 下落]] | E75: =IF(F75<>"",HYPERLINK(F75,"→"),"") -> → | F75: =IFERROR(VLOOKUP(A75,红宝书去重版!$A:$S,11,FALSE),"") -> F:\《自创文法查阅Excel》4.1备份\《B词汇·红宝书》\红宝书15版图片\2970-げらく【下落】.jpg | G75: =IF(H75<>"",HYPERLINK(H75,"▶"),"") -> ▶ | H75: =IFERROR(VLOOKUP(A75,红宝书去重版!$A:$S,18,FALSE),"") -> F:\《自创文法查阅Excel》4.1备份\《B词汇·红宝书》\红宝书MP3分割\09 n1-け (51).mp3
A76: 6283 | B76: ついらく | C76: 墜落 | D76: =IF(A76<>"",A76&" "&"[["&B76&" "&C76&"]]","") -> 6283 [[ついらく 墜落]] | E76: =IF(F76<>"",HYPERLINK(F76,"→"),"") -> → | F76: =IFERROR(VLOOKUP(A76,红宝书去重版!$A:$S,11,FALSE),"") -> F:\《自创文法查阅Excel》4.1备份\《B词汇·红宝书》\红宝书15版图片\6283-ついらく【墜落】.jpg | G76: =IF(H76<>"",HYPERLINK(H76,"▶"),"") -> ▶ | H76: =IFERROR(VLOOKUP(A76,红宝书去重版!$A:$S,18,FALSE),"") -> F:\《自创文法查阅Excel》4.1备份\《B词汇·红宝书》\红宝书MP3分割\18 n1-つ (5).mp3
A77: 6573 | B77: てんらく | C77: 転落 | D77: =IF(A77<>"",A77&" "&"[["&B77&" "&C77&"]]","") -> 6573 [[てんらく 転落]] | E77: =IF(F77<>"",HYPERLINK(F77,"→"),"") -> → | F77: =IFERROR(VLOOKUP(A77,红宝书去重版!$A:$S,11,FALSE),"") -> F:\《自创文法查阅Excel》4.1备份\《B词汇·红宝书》\红宝书15版图片\6573-てんらく【転落】.jpg | G77: =IF(H77<>"",HYPERLINK(H77,"▶"),"") -> ▶ | H77: =IFERROR(VLOOKUP(A77,红宝书去重版!$A:$S,18,FALSE),"") -> F:\《自创文法查阅Excel》4.1备份\《B词汇·红宝书》\红宝书MP3分割\19 n1-て (80).mp3
A78: 8676 | B78: ぼつらく | C78: 没落 | D78: =IF(A78<>"",A78&" "&"[["&B78&" "&C78&"]]","") -> 8676 [[ぼつらく 没落]] | E78: =IF(F78<>"",HYPERLINK(F78,"→"),"") -> → | F78: =IFERROR(VLOOKUP(A78,红宝书去重版!$A:$S,11,FALSE),"") -> F:\《自创文法查阅Excel》4.1备份\《B词汇·红宝书》\红宝书15版图片\8676-ぼつらく【没落】.jpg | G78: =IF(H78<>"",HYPERLINK(H78,"▶"),"") -> ▶ | H78: =IFERROR(VLOOKUP(A78,红宝书去重版!$A:$S,18,FALSE),"") -> F:\《自创文法查阅Excel》4.1备份\《B词汇·红宝书》\红宝书MP3分割\30 n1-ほ (56).mp3
A79: 9747 | B79: らくだい | C79: 落第 | D79: =IF(A79<>"",A79&" "&"[["&B79&" "&C79&"]]","") -> 9747 [[らくだい 落第]] | E79: =IF(F79<>"",HYPERLINK(F79,"→"),"") -> → | F79: =IFERROR(VLOOKUP(A79,红宝书去重版!$A:$S,11,FALSE),"") -> F:\《自创文法查阅Excel》4.1备份\《B词汇·红宝书》\红宝书15版图片\9747-らくだい【落第】.jpg | G79: =IF(H79<>"",HYPERLINK(H79,"▶"),"") -> ▶ | H79: =IFERROR(VLOOKUP(A79,红宝书去重版!$A:$S,18,FALSE),"") -> F:\《自创文法查阅Excel》4.1备份\《B词汇·红宝书》\红宝书MP3分割\41 n2-ら (4).mp3
A80: 9756 | B80: らくがき | C80: 落書き | D80: =IF(A80<>"",A80&" "&"[["&B80&" "&C80&"]]","") -> 9756 [[らくがき 落書き]] | E80: =IF(F80<>"",HYPERLINK(F80,"→"),"") -> → | F80: =IFERROR(VLOOKUP(A80,红宝书去重版!$A:$S,11,FALSE),"") -> F:\《自创文法查阅Excel》4.1备份\《B词汇·红宝书》\红宝书15版图片\9756-らくがき【落書き】.jpg | G80: =IF(H80<>"",HYPERLINK(H80,"▶"),"") -> ▶ | H80: =IFERROR(VLOOKUP(A80,红宝书去重版!$A:$S,18,FALSE),"") -> F:\《自创文法查阅Excel》4.1备份\《B词汇·红宝书》\红宝书MP3分割\41 n1-ら (5).mp3
A81: 9757 | B81: らくたん | C81: 落胆 | D81: =IF(A81<>"",A81&" "&"[["&B81&" "&C81&"]]","") -> 9757 [[らくたん 落胆]] | E81: =IF(F81<>"",HYPERLINK(F81,"→"),"") -> → | F81: =IFERROR(VLOOKUP(A81,红宝书去重版!$A:$S,11,FALSE),"") -> F:\《自创文法查阅Excel》4.1备份\《B词汇·红宝书》\红宝书15版图片\9757-らくたん【落胆】.jpg | G81: =IF(H81<>"",HYPERLINK(H81,"▶"),"") -> ▶ | H81: =IFERROR(VLOOKUP(A81,红宝书去重版!$A:$S,18,FALSE),"") -> F:\《自创文法查阅Excel》4.1备份\《B词汇·红宝书》\红宝书MP3分割\41 n1-ら (6).mp3
D82: =IF(A82<>"",A82&" "&"[["&B82&" "&C82&"]]","") | E82: =IF(F82<>"",HYPERLINK(F82,"→"),"") | F82: =IFERROR(VLOOKUP(A82,红宝书去重版!$A:$S,11,FALSE),"") | G82: =IF(H82<>"",HYPERLINK(H82,"▶"),"") | H82: =IFERROR(VLOOKUP(A82,红宝书去重版!$A:$S,18,FALSE),"")
A83: 9762 | B83: らっか | C83: 落下 | D83: =IF(A83<>"",A83&" "&"[["&B83&" "&C83&"]]","") -> 9762 [[らっか 落下]] | E83: =IF(F83<>"",HYPERLINK(F83,"→"),"") -> → | F83: =IFERROR(VLOOKUP(A83,红宝书去重版!$A:$S,11,FALSE),"") -> F:\《自创文法查阅Excel》4.1备份\《B词汇·红宝书》\红宝书15版图片\9762-らっか【落下】.jpg | G83: =IF(H83<>"",HYPERLINK(H83,"▶"),"") -> ▶ | H83: =IFERROR(VLOOKUP(A83,红宝书去重版!$A:$S,18,FALSE),"") -> F:\《自创文法查阅Excel》4.1备份\《B词汇·红宝书》\红宝书MP3分割\41 n1-ら (11).mp3
D84: =IF(A84<>"",A84&" "&"[["&B84&" "&C84&"]]","") | E84: =IF(F84<>"",HYPERLINK(F84,"→"),"") | F84: =IFERROR(VLOOKUP(A84,红宝书去重版!$A:$S,11,FALSE),"") | G84: =IF(H84<>"",HYPERLINK(H84,"▶"),"") | H84: =IFERROR(VLOOKUP(A84,红宝书去重版!$A:$S,18,FALSE),"")
A85: 1131 | B85: おちる | C85: 落ちる | D85: =IF(A85<>"",A85&" "&"[["&B85&" "&C85&"]]","") -> 1131 [[おちる 落ちる]] | E85: =IF(F85<>"",HYPERLINK(F85,"→"),"") -> → | F85: =IFERROR(VLOOKUP(A85,红宝书去重版!$A:$S,11,FALSE),"") -> F:\《自创文法查阅Excel》4.1备份\《B词汇·红宝书》\红宝书15版图片\1131-おちる【落ちる】.jpg | G85: =IF(H85<>"",HYPERLINK(H85,"▶"),"") -> ▶ | H85: =IFERROR(VLOOKUP(A85,红宝书去重版!$A:$S,18,FALSE),"") -> F:\《自创文法查阅Excel》4.1备份\《B词汇·红宝书》\红宝书MP3分割\05 n4-お (31).mp3
A86: 1203 | B86: おちつく | C86: 落ち着く | D86: =IF(A86<>"",A86&" "&"[["&B86&" "&C86&"]]","") -> 1203 [[おちつく 落ち着く]] | E86: =IF(F86<>"",HYPERLINK(F86,"→"),"") -> → | F86: =IFERROR(VLOOKUP(A86,红宝书去重版!$A:$S,11,FALSE),"") -> F:\《自创文法查阅Excel》4.1备份\《B词汇·红宝书》\红宝书15版图片\1203-おちつく【落ち着く】.jpg | G86: =IF(H86<>"",HYPERLINK(H86,"▶"),"") -> ▶ | H86: =IFERROR(VLOOKUP(A86,红宝书去重版!$A:$S,18,FALSE),"") -> F:\《自创文法查阅Excel》4.1备份\《B词汇·红宝书》\红宝书MP3分割\05 n3-お (39).mp3
A87: 1267 | B87: おちこむ | C87: 落ち込む | D87: =IF(A87<>"",A87&" "&"[["&B87&" "&C87&"]]","") -> 1267 [[おちこむ 落ち込む]] | E87: =IF(F87<>"",HYPERLINK(F87,"→"),"") -> → | F87: =IFERROR(VLOOKUP(A87,红宝书去重版!$A:$S,11,FALSE),"") -> F:\《自创文法查阅Excel》4.1备份\《B词汇·红宝书》\红宝书15版图片\1267-おちこむ【落ち込む】.jpg | G87: =IF(H87<>"",HYPERLINK(H87,"▶"),"") -> ▶ | H87: =IFERROR(VLOOKUP(A87,红宝书去重版!$A:$S,18,FALSE),"") -> F:\《自创文法查阅Excel》4.1备份\《B词汇·红宝书》\红宝书MP3分割\05 n2-お (44).mp3
A88: 1366 | B88: おちど | C88: 落ち度 | D88: =IF(A88<>"",A88&" "&"[["&B88&" "&C88&"]]","") -> 1366 [[おちど 落ち度]] | E88: =IF(F88<>"",HYPERLINK(F88,"→"),"") -> → | F88: =IFERROR(VLOOKUP(A88,红宝书去重版!$A:$S,11,FALSE),"") -> F:\《自创文法查阅Excel》4.1备份\《B词汇·红宝书》\红宝书15版图片\1366-おちど【落ち度】.jpg | G88: =IF(H88<>"",HYPERLINK(H88,"▶"),"") -> ▶ | H88: =IFERROR(VLOOKUP(A88,红宝书去重版!$A:$S,18,FALSE),"") -> F:\《自创文法查阅Excel》4.1备份\《B词汇·红宝书》\红宝书MP3分割\05 n1-お (62).mp3
A89: 1135 | B89: おとす | C89: 落とす | D89: =IF(A89<>"",A89&" "&"[["&B89&" "&C89&"]]","") -> 1135 [[おとす 落とす]] | E89: =IF(F89<>"",HYPERLINK(F89,"→"),"") -> → | F89: =IFERROR(VLOOKUP(A89,红宝书去重版!$A:$S,11,FALSE),"") -> F:\《自创文法查阅Excel》4.1备份\《B词汇·红宝书》\红宝书15版图片\1135-おとす【落とす】.jpg | G89: =IF(H89<>"",HYPERLINK(H89,"▶"),"") -> ▶ | H89: =IFERROR(VLOOKUP(A89,红宝书去重版!$A:$S,18,FALSE),"") -> F:\《自创文法查阅Excel》4.1备份\《B词汇·红宝书》\红宝书MP3分割\05 n4-お (35).mp3
A90: 9002 | B90: みおとす | C90: 見落とす | D90: =IF(A90<>"",A90&" "&"[["&B90&" "&C90&"]]","") -> 9002 [[みおとす 見落とす]] | E90: =IF(F90<>"",HYPERLINK(F90,"→"),"") -> → | F90: =IFERROR(VLOOKUP(A90,红宝书去重版!$A:$S,11,FALSE),"") -> F:\《自创文法查阅Excel》4.1备份\《B词汇·红宝书》\红宝书15版图片\9002-みおとす【見落とす】.jpg | G90: =IF(H90<>"",HYPERLINK(H90,"▶"),"") -> ▶ | H90: =IFERROR(VLOOKUP(A90,红宝书去重版!$A:$S,18,FALSE),"") -> F:\《自创文法查阅Excel》4.1备份\《B词汇·红宝书》\红宝书MP3分割\32 n1-み (6).mp3
A91: 1269 | B91: おとしもの | C91: 落し物 | D91: =IF(A91<>"",A91&" "&"[["&B91&" "&C91&"]]","") -> 1269 [[おとしもの 落し物]] | E91: =IF(F91<>"",HYPERLINK(F91,"→"),"") -> → | F91: =IFERROR(VLOOKUP(A91,红宝书去重版!$A:$S,11,FALSE),"") -> F:\《自创文法查阅Excel》4.1备份\《B词汇·红宝书》\红宝书15版图片\1269-おとしもの【落し物】.jpg | G91: =IF(H91<>"",HYPERLINK(H91,"▶"),"") -> ▶ | H91: =IFERROR(VLOOKUP(A91,红宝书去重版!$A:$S,18,FALSE),"") -> F:\《自创文法查阅Excel》4.1备份\《B词汇·红宝书》\红宝书MP3分割\05 n2-お (46).mp3
D92: =IF(A92<>"",A92&" "&"[["&B92&" "&C92&"]]","") | E92: =IF(F92<>"",HYPERLINK(F92,"→"),"") | F92: =IFERROR(VLOOKUP(A92,红宝书去重版!$A:$S,11,FALSE),"") | G92: =IF(H92<>"",HYPERLINK(H92,"▶"),"") | H92: =IFERROR(VLOOKUP(A92,红宝书去重版!$A:$S,18,FALSE),"")
A93: 1197 | B93: おしゃれ | C93: 御洒落 | D93: =IF(A93<>"",A93&" "&"[["&B93&" "&C93&"]]","") -> 1197 [[おしゃれ 御洒落]] | E93: =IF(F93<>"",HYPERLINK(F93,"→"),"") -> → | F93: =IFERROR(VLOOKUP(A93,红宝书去重版!$A:$S,11,FALSE),"") -> F:\《自创文法查阅Excel》4.1备份\《B词汇·红宝书》\红宝书15版图片\1197-おしゃれ【御洒落】.jpg | G93: =IF(H93<>"",HYPERLINK(H93,"▶"),"") -> ▶ | H93: =IFERROR(VLOOKUP(A93,红宝书去重版!$A:$S,18,FALSE),"") -> F:\《自创文法查阅Excel》4.1备份\《B词汇·红宝书》\红宝书MP3分割\05 n3-お (33).mp3
D94: =IF(A94<>"",A94&" "&"[["&B94&" "&C94&"]]","") | E94: =IF(F94<>"",HYPERLINK(F94,"→"),"") | F94: =IFERROR(VLOOKUP(A94,红宝书去重版!$A:$S,11,FALSE),"") | G94: =IF(H94<>"",HYPERLINK(H94,"▶"),"") | H94: =IFERROR(VLOOKUP(A94,红宝书去重版!$A:$S,18,FALSE),"")
A95: 2091 | B95: がんせき | C95: 岩石 | D95: =IF(A95<>"",A95&" "&"[["&B95&" "&C95&"]]","") -> 2091 [[がんせき 岩石]] | E95: =IF(F95<>"",HYPERLINK(F95,"→"),"") -> → | F95: =IFERROR(VLOOKUP(A95,红宝书去重版!$A:$S,11,FALSE),"") -> F:\《自创文法查阅Excel》4.1备份\《B词汇·红宝书》\红宝书15版图片\2091-がんせき【岩石】.jpg | G95: =IF(H95<>"",HYPERLINK(H95,"▶"),"") -> ▶ | H95: =IFERROR(VLOOKUP(A95,红宝书去重版!$A:$S,18,FALSE),"") -> F:\《自创文法查阅Excel》4.1备份\《B词汇·红宝书》\红宝书MP3分割\06 n1-か (190).mp3
A96: 3355 | B96: こうせき | C96: 鉱石 | D96: =IF(A96<>"",A96&" "&"[["&B96&" "&C96&"]]","") -> 3355 [[こうせき 鉱石]] | E96: =IF(F96<>"",HYPERLINK(F96,"→"),"") -> → | F96: =IFERROR(VLOOKUP(A96,红宝书去重版!$A:$S,11,FALSE),"") -> F:\《自创文法查阅Excel》4.1备份\《B词汇·红宝书》\红宝书15版图片\3355-こうせき【鉱石】.jpg | G96: =IF(H96<>"",HYPERLINK(H96,"▶"),"") -> ▶ | H96: =IFERROR(VLOOKUP(A96,红宝书去重版!$A:$S,18,FALSE),"") -> F:\《自创文法查阅Excel》4.1备份\《B词汇·红宝书》\红宝书MP3分割\10 n1-こ (33).mp3
A97: 5082 | B97: せきたん | C97: 石炭 | D97: =IF(A97<>"",A97&" "&"[["&B97&" "&C97&"]]","") -> 5082 [[せきたん 石炭]] | E97: =IF(F97<>"",HYPERLINK(F97,"→"),"") -> → | F97: =IFERROR(VLOOKUP(A97,红宝书去重版!$A:$S,11,FALSE),"") -> F:\《自创文法查阅Excel》4.1备份\《B词汇·红宝书》\红宝书15版图片\5082-せきたん【石炭】.jpg | G97: =IF(H97<>"",HYPERLINK(H97,"▶"),"") -> ▶ | H97: =IFERROR(VLOOKUP(A97,红宝书去重版!$A:$S,18,FALSE),"") -> F:\《自创文法查阅Excel》4.1备份\《B词汇·红宝书》\红宝书MP3分割\14 n3-せ (31).mp3
A98: 5084 | B98: せきゆ | C98: 石油 | D98: =IF(A98<>"",A98&" "&"[["&B98&" "&C98&"]]","") -> 5084 [[せきゆ 石油]] | E98: =IF(F98<>"",HYPERLINK(F98,"→"),"") -> → | F98: =IFERROR(VLOOKUP(A98,红宝书去重版!$A:$S,11,FALSE),"") -> F:\《自创文法查阅Excel》4.1备份\《B词汇·红宝书》\红宝书15版图片\5084-せきゆ【石油】.jpg | G98: =IF(H98<>"",HYPERLINK(H98,"▶"),"") -> ▶ | H98: =IFERROR(VLOOKUP(A98,红宝书去重版!$A:$S,18,FALSE),"") -> F:\《自创文法查阅Excel》4.1备份\《B词汇·红宝书》\红宝书MP3分割\14 n3-せ (33).mp3
A99: 8576 | B99: ほうせき | C99: 宝石 | D99: =IF(A99<>"",A99&" "&"[["&B99&" "&C99&"]]","") -> 8576 [[ほうせき 宝石]] | E99: =IF(F99<>"",HYPERLINK(F99,"→"),"") -> → | F99: =IFERROR(VLOOKUP(A99,红宝书去重版!$A:$S,11,FALSE),"") -> F:\《自创文法查阅Excel》4.1备份\《B词汇·红宝书》\红宝书15版图片\8576-ほうせき【宝石】.jpg | G99: =IF(H99<>"",HYPERLINK(H99,"▶"),"") -> ▶ | H99: =IFERROR(VLOOKUP(A99,红宝书去重版!$A:$S,18,FALSE),"") -> F:\《自创文法查阅Excel》4.1备份\《B词汇·红宝书》\红宝书MP3分割\30 n2-ほ (13).mp3
D100: =IF(A100<>"",A100&" "&"[["&B100&" "&C100&"]]","") | E100: =IF(F100<>"",HYPERLINK(F100,"→"),"") | F100: =IFERROR(VLOOKUP(A100,红宝书去重版!$A:$S,11,FALSE),"") | G100: =IF(H100<>"",HYPERLINK(H100,"▶"),"") | H100: =IFERROR(VLOOKUP(A100,红宝书去重版!$A:$S,18,FALSE),"")
A101: 5014 | B101: せっけん | C101: 石鹸 | D101: =IF(A101<>"",A101&" "&"[["&B101&" "&C101&"]]","") -> 5014 [[せっけん 石鹸]] | E101: =IF(F101<>"",HYPERLINK(F101,"→"),"") -> → | F101: =IFERROR(VLOOKUP(A101,红宝书去重版!$A:$S,11,FALSE),"") -> F:\《自创文法查阅Excel》4.1备份\《B词汇·红宝书》\红宝书15版图片\5014-せっけん【石鹸】.jpg | G101: =IF(H101<>"",HYPERLINK(H101,"▶"),"") -> ▶ | H101: =IFERROR(VLOOKUP(A101,红宝书去重版!$A:$S,18,FALSE),"") -> F:\《自创文法查阅Excel》4.1备份\《B词汇·红宝书》\红宝书MP3分割\14 n5-せ (11).mp3
D102: =IF(A102<>"",A102&" "&"[["&B102&" "&C102&"]]","") | E102: =IF(F102<>"",HYPERLINK(F102,"→"),"") | F102: =IFERROR(VLOOKUP(A102,红宝书去重版!$A:$S,11,FALSE),"") | G102: =IF(H102<>"",HYPERLINK(H102,"▶"),"") | H102: =IFERROR(VLOOKUP(A102,红宝书去重版!$A:$S,18,FALSE),"")
A103: 442 | B103: いし | C103: 石 | D103: =IF(A103<>"",A103&" "&"[["&B103&" "&C103&"]]","") -> 442 [[いし 石]] | E103: =IF(F103<>"",HYPERLINK(F103,"→"),"") -> → | F103: =IFERROR(VLOOKUP(A103,红宝书去重版!$A:$S,11,FALSE),"") -> F:\《自创文法查阅Excel》4.1备份\《B词汇·红宝书》\红宝书15版图片\442-いし【石】.jpg | G103: =IF(H103<>"",HYPERLINK(H103,"▶"),"") -> ▶ | H103: =IFERROR(VLOOKUP(A103,红宝书去重版!$A:$S,18,FALSE),"") -> F:\《自创文法查阅Excel》4.1备份\《B词汇·红宝书》\红宝书MP3分割\02 n4-い (13).mp3
...

Sheet Sheet1

Sheet 词典存放目录
A1: F:\《自创文法查阅Excel》4.1备份\《B词汇·红宝书》 | B1: ←填入文件夹地址
